Workbook

Sheet Precios_Para_Comunicar
A1: Nombre_Comercial | B1: Producto | C1: Color | D1: Categoria | E1: Costo | F1: B2C | G1: Muestra | H1: Partner (1u) | I1: Starter (5-9u) | J1: Pro (10-20u) | K1: Drop (30-99u) | L1: Bulk (100+u) | M1: Margen%_Partner | N1: Margen%_Starter | O1: Margen%_Pro | P1: Margen%_Drop | Q1: Margen%_Bulk
B2: Buzo Cuello Redondo | C2: Blanco | D2: crewneck | E2: =Detalle_SKU_Con_Margenes!F2 -> 24100 | F2: 43000 | G2: 32200 | H2: =Detalle_SKU_Con_Margenes!I2 -> 32200 | I2: =Detalle_SKU_Con_Margenes!J2 -> 31200 | J2: =Detalle_SKU_Con_Margenes!K2 -> 30200 | K2: =Detalle_SKU_Con_Margenes!L2 -> 29200 | L2: =Detalle_SKU_Con_Margenes!M2 -> 28200 | M2: =(H2-$E2)/H2 -> 0.2515528 | N2: =(I2-$E2)/I2 -> 0.2275641 | O2: =(J2-$E2)/J2 -> 0.20198675 | P2: =(K2-$E2)/K2 -> 0.17465753 | Q2: =(L2-$E2)/L2 -> 0.14539007
B3: Buzo Cuello Redondo | C3: Negro | D3: crewneck | E3: =Detalle_SKU_Con_Margenes!F8 -> 28170 | F3: 43000 | G3: 32200 | H3: =Detalle_SKU_Con_Margenes!I8 -> 32200 | I3: =Detalle_SKU_Con_Margenes!J8 -> 31200 | J3: =Detalle_SKU_Con_Margenes!K8 -> 30200 | K3: =Detalle_SKU_Con_Margenes!L8 -> 29200 | L3: =Detalle_SKU_Con_Margenes!M8 -> 28200 | M3: =(H3-$E3)/H3 -> 0.12515528 | N3: =(I3-$E3)/I3 -> 0.097115385 | O3: =(J3-$E3)/J3 -> 0.067218543 | P3: =(K3-$E3)/K3 -> 0.035273973 | Q3: =(L3-$E3)/L3 -> 0.0010638298
B4: Buzo Cuello Redondo | C4: Stone Wash | D4: crewneck | E4: =Detalle_SKU_Con_Margenes!F14 -> 28170 | F4: 43000 | G4: 32200 | H4: =Detalle_SKU_Con_Margenes!I14 -> 32200 | I4: =Detalle_SKU_Con_Margenes!J14 -> 31200 | J4: =Detalle_SKU_Con_Margenes!K14 -> 30200 | K4: =Detalle_SKU_Con_Margenes!L14 -> 29200 | L4: =Detalle_SKU_Con_Margenes!M14 -> 28200 | M4: =(H4-$E4)/H4 -> 0.12515528 | N4: =(I4-$E4)/I4 -> 0.097115385 | O4: =(J4-$E4)/J4 -> 0.067218543 | P4: =(K4-$E4)/K4 -> 0.035273973 | Q4: =(L4-$E4)/L4 -> 0.0010638298
B5: Buzo Hoodie Unisex | C5: Blanco | D5: hoodie | E5: =Detalle_SKU_Con_Margenes!F20 -> 25100 | F5: 55000 | G5: 38700 | H5: =Detalle_SKU_Con_Margenes!I20 -> 38700 | I5: =Detalle_SKU_Con_Margenes!J20 -> 36600 | J5: =Detalle_SKU_Con_Margenes!K20 -> 34500 | K5: =Detalle_SKU_Con_Margenes!L20 -> 32400 | L5: =Detalle_SKU_Con_Margenes!M20 -> 30300 | M5: =(H5-$E5)/H5 -> 0.35142119 | N5: =(I5-$E5)/I5 -> 0.31420765 | O5: =(J5-$E5)/J5 -> 0.27246377 | P5: =(K5-$E5)/K5 -> 0.22530864 | Q5: =(L5-$E5)/L5 -> 0.17161716
B6: Buzo Hoodie Unisex | C6: Negro | D6: hoodie | E6: =Detalle_SKU_Con_Margenes!F26 -> 29170 | F6: 55000 | G6: 38700 | H6: =Detalle_SKU_Con_Margenes!I26 -> 38700 | I6: =Detalle_SKU_Con_Margenes!J26 -> 36600 | J6: =Detalle_SKU_Con_Margenes!K26 -> 34500 | K6: =Detalle_SKU_Con_Margenes!L26 -> 32400 | L6: =Detalle_SKU_Con_Margenes!M26 -> 30300 | M6: =(H6-$E6)/H6 -> 0.24625323 | N6: =(I6-$E6)/I6 -> 0.20300546 | O6: =(J6-$E6)/J6 -> 0.15449275 | P6: =(K6-$E6)/K6 -> 0.099691358 | Q6: =(L6-$E6)/L6 -> 0.037293729
B7: Buzo Hoodie Unisex | C7: Stone Wash | D7: hoodie | E7: =Detalle_SKU_Con_Margenes!F32 -> 30170 | F7: 55000 | G7: 38700 | H7: =Detalle_SKU_Con_Margenes!I32 -> 38700 | I7: =Detalle_SKU_Con_Margenes!J32 -> 36600 | J7: =Detalle_SKU_Con_Margenes!K32 -> 34500 | K7: =Detalle_SKU_Con_Margenes!L32 -> 32400 | L7: =Detalle_SKU_Con_Margenes!M32 -> 30300 | M7: =(H7-$E7)/H7 -> 0.22041344 | N7: =(I7-$E7)/I7 -> 0.17568306 | O7: =(J7-$E7)/J7 -> 0.12550725 | P7: =(K7-$E7)/K7 -> 0.06882716 | Q7: =(L7-$E7)/L7 -> 0.004290429
B8: Buzo Hoodie Unisex | C8: Caramel | D8: hoodie | E8: =Detalle_SKU_Con_Margenes!F38 -> 29170 | F8: 55000 | G8: 38700 | H8: =Detalle_SKU_Con_Margenes!I38 -> 38700 | I8: =Detalle_SKU_Con_Margenes!J38 -> 36600 | J8: =Detalle_SKU_Con_Margenes!K38 -> 34500 | K8: =Detalle_SKU_Con_Margenes!L38 -> 32400 | L8: =Detalle_SKU_Con_Margenes!M38 -> 30300 | M8: =(H8-$E8)/H8 -> 0.24625323 | N8: =(I8-$E8)/I8 -> 0.20300546 | O8: =(J8-$E8)/J8 -> 0.15449275 | P8: =(K8-$E8)/K8 -> 0.099691358 | Q8: =(L8-$E8)/L8 -> 0.037293729
B9: Buzo Hoodie Unisex | C9: Crema | D9: hoodie | E9: =Detalle_SKU_Con_Margenes!F43 -> 29170 | F9: 55000 | G9: 38700 | H9: =Detalle_SKU_Con_Margenes!I43 -> 38700 | I9: =Detalle_SKU_Con_Margenes!J43 -> 36600 | J9: =Detalle_SKU_Con_Margenes!K43 -> 34500 | K9: =Detalle_SKU_Con_Margenes!L43 -> 32400 | L9: =Detalle_SKU_Con_Margenes!M43 -> 30300 | M9: =(H9-$E9)/H9 -> 0.24625323 | N9: =(I9-$E9)/I9 -> 0.20300546 | O9: =(J9-$E9)/J9 -> 0.15449275 | P9: =(K9-$E9)/K9 -> 0.099691358 | Q9: =(L9-$E9)/L9 -> 0.037293729
B10: Buzo Hoodie Unisex | C10: Gris Melange | D10: hoodie | E10: =Detalle_SKU_Con_Margenes!F48 -> 29170 | F10: 55000 | G10: 38700 | H10: =Detalle_SKU_Con_Margenes!I48 -> 38700 | I10: =Detalle_SKU_Con_Margenes!J48 -> 36600 | J10: =Detalle_SKU_Con_Margenes!K48 -> 34500 | K10: =Detalle_SKU_Con_Margenes!L48 -> 32400 | L10: =Detalle_SKU_Con_Margenes!M48 -> 30300 | M10: =(H10-$E10)/H10 -> 0.24625323 | N10: =(I10-$E10)/I10 -> 0.20300546 | O10: =(J10-$E10)/J10 -> 0.15449275 | P10: =(K10-$E10)/K10 -> 0.099691358 | Q10: =(L10-$E10)/L10 -> 0.037293729
B11: Aura Oversize T-Shirt | C11: Blanco | D11: tee_oversize | E11: =Detalle_SKU_Con_Margenes!F53 -> 19000 | F11: 31000 | G11: 25400 | H11: 26600 | I11: 25900 | J11: 25100 | K11: 24300 | L11: 23600 | M11: =(H11-$E11)/H11 -> 0.28571429 | N11: =(I11-$E11)/I11 -> 0.26640927 | O11: =(J11-$E11)/J11 -> 0.24302789 | P11: =(K11-$E11)/K11 -> 0.218107 | Q11: =(L11-$E11)/L11 -> 0.19491525
B12: Aura Oversize T-Shirt | C12: Caramel | D12: tee_oversize | E12: =Detalle_SKU_Con_Margenes!F60 -> 23070 | F12: 31000 | G12: 25400 | H12: 26600 | I12: 25900 | J12: 25100 | K12: 24300 | L12: 23600 | M12: =(H12-$E12)/H12 -> 0.13270677 | N12: =(I12-$E12)/I12 -> 0.10926641 | O12: =(J12-$E12)/J12 -> 0.080876494 | P12: =(K12-$E12)/K12 -> 0.050617284 | Q12: =(L12-$E12)/L12 -> 0.022457627
B13: Aura Oversize T-Shirt | C13: Negro | D13: tee_oversize | E13: =Detalle_SKU_Con_Margenes!F64 -> 23070 | F13: 31000 | G13: 25400 | H13: 26600 | I13: 25900 | J13: 25100 | K13: 24300 | L13: 23600 | M13: =(H13-$E13)/H13 -> 0.13270677 | N13: =(I13-$E13)/I13 -> 0.10926641 | O13: =(J13-$E13)/J13 -> 0.080876494 | P13: =(K13-$E13)/K13 -> 0.050617284 | Q13: =(L13-$E13)/L13 -> 0.022457627
B14: Aura Oversize T-Shirt | C14: Stone Wash | D14: tee_oversize | E14: =Detalle_SKU_Con_Margenes!F71 -> 23470 | F14: 31000 | G14: 25400 | H14: 26600 | I14: 25900 | J14: 25100 | K14: 24300 | L14: 23600 | M14: =(H14-$E14)/H14 -> 0.11766917 | N14: =(I14-$E14)/I14 -> 0.093822394 | O14: =(J14-$E14)/J14 -> 0.064940239 | P14: =(K14-$E14)/K14 -> 0.034156379 | Q14: =(L14-$E14)/L14 -> 0.0055084746
B15: Aldea Classic Fit T-Shirt | C15: Blanco | D15: tee_classic | E15: =Detalle_SKU_Con_Margenes!F75 -> 18600 | F15: 28600 | G15: 25700 | H15: 25800 | I15: 25100 | J15: 24400 | K15: 23800 | L15: 23600 | M15: =(H15-$E15)/H15 -> 0.27906977 | N15: =(I15-$E15)/I15 -> 0.25896414 | O15: =(J15-$E15)/J15 -> 0.23770492 | P15: =(K15-$E15)/K15 -> 0.21848739 | Q15: =(L15-$E15)/L15 -> 0.21186441
B16: Aldea Classic Fit T-Shirt | C16: Negro | D16: tee_classic | E16: =Detalle_SKU_Con_Margenes!F80 -> 22670 | F16: 28600 | G16: 25700 | H16: 25800 | I16: 25100 | J16: 24400 | K16: 23800 | L16: 23600 | M16: =(H16-$E16)/H16 -> 0.12131783 | N16: =(I16-$E16)/I16 -> 0.096812749 | O16: =(J16-$E16)/J16 -> 0.070901639 | P16: =(K16-$E16)/K16 -> 0.047478992 | Q16: =(L16-$E16)/L16 -> 0.03940678
B17: Remera Clásica Mujer | C17: Blanca | D17: tee_classic | E17: =Detalle_SKU_Con_Margenes!F85 -> 18600 | F17: 28600 | G17: 25700 | H17: 25800 | I17: 25100 | J17: 24400 | K17: 23800 | L17: 23600 | M17: =(H17-$E17)/H17 -> 0.27906977 | N17: =(I17-$E17)/I17 -> 0.25896414 | O17: =(J17-$E17)/J17 -> 0.23770492 | P17: =(K17-$E17)/K17 -> 0.21848739 | Q17: =(L17-$E17)/L17 -> 0.21186441
B18: Remera Clásica Mujer | C18: Negra | D18: tee_classic | E18: =Detalle_SKU_Con_Margenes!F90 -> 22670 | F18: 28600 | G18: 25700 | H18: 25800 | I18: 25100 | J18: 24400 | K18: 23800 | L18: 23600 | M18: =(H18-$E18)/H18 -> 0.12131783 | N18: =(I18-$E18)/I18 -> 0.096812749 | O18: =(J18-$E18)/J18 -> 0.070901639 | P18: =(K18-$E18)/K18 -> 0.047478992 | Q18: =(L18-$E18)/L18 -> 0.03940678
B19: Remera Crop Mujer | C19: Amarillo | D19: crop | E19: =Detalle_SKU_Con_Margenes!F95 -> 18100 | F19: 23500 | G19: 19300 | H19: 20800 | I19: 20300 | J19: 19800 | K19: 19300 | L19: 18900 | M19: =(H19-$E19)/H19 -> 0.12980769 | N19: =(I19-$E19)/I19 -> 0.10837438 | O19: =(J19-$E19)/J19 -> 0.085858586 | P19: =(K19-$E19)/K19 -> 0.062176166 | Q19: =(L19-$E19)/L19 -> 0.042328042
B20: Remera Crop Mujer | C20: Chocolate | D20: crop | E20: =Detalle_SKU_Con_Margenes!F100 -> 18100 | F20: 23500 | G20: 19300 | H20: 20800 | I20: 20300 | J20: 19800 | K20: 19300 | L20: 18900 | M20: =(H20-$E20)/H20 -> 0.12980769 | N20: =(I20-$E20)/I20 -> 0.10837438 | O20: =(J20-$E20)/J20 -> 0.085858586 | P20: =(K20-$E20)/K20 -> 0.062176166 | Q20: =(L20-$E20)/L20 -> 0.042328042
B21: Remera Crop Mujer | C21: Gris Melange | D21: crop | E21: =Detalle_SKU_Con_Margenes!F105 -> 18100 | F21: 23500 | G21: 19300 | H21: 20800 | I21: 20300 | J21: 19800 | K21: 19300 | L21: 18900 | M21: =(H21-$E21)/H21 -> 0.12980769 | N21: =(I21-$E21)/I21 -> 0.10837438 | O21: =(J21-$E21)/J21 -> 0.085858586 | P21: =(K21-$E21)/K21 -> 0.062176166 | Q21: =(L21-$E21)/L21 -> 0.042328042
B22: Remera Crop Mujer | C22: Negra | D22: crop | E22: =Detalle_SKU_Con_Margenes!F95 -> 18100 | F22: 23500 | G22: 19300 | H22: 20800 | I22: 20300 | J22: 19800 | K22: 19300 | L22: 18900 | M22: =(H22-$E22)/H22 -> 0.12980769 | N22: =(I22-$E22)/I22 -> 0.10837438 | O22: =(J22-$E22)/J22 -> 0.085858586 | P22: =(K22-$E22)/K22 -> 0.062176166 | Q22: =(L22-$E22)/L22 -> 0.042328042
B23: Musculosa Bali | C23: Blanca | D23: tank | E23: ='Precios Tab Dreamfull-sheets'!$G$12 -> 18100 | F23: 21800 | G23: =H23 -> 20800 | H23: 20800 | I23: 20700 | J23: 20500 | K23: 20300 | L23: 20100 | M23: =(H23-$E23)/H23 -> 0.12980769 | N23: =(I23-$E23)/I23 -> 0.12560386 | O23: =(J23-$E23)/J23 -> 0.11707317 | P23: =(K23-$E23)/K23 -> 0.10837438 | Q23: =(L23-$E23)/L23 -> 0.099502488
B24: Musculosa Bali | C24: Gris | D24: tank | E24: ='Precios Tab Dreamfull-sheets'!$G$12 -> 18100 | F24: 21800 | G24: =H24 -> 20800 | H24: 20800 | I24: 20700 | J24: 20500 | K24: 20300 | L24: 20100 | M24: =(H24-$E24)/H24 -> 0.12980769 | N24: =(I24-$E24)/I24 -> 0.12560386 | O24: =(J24-$E24)/J24 -> 0.11707317 | P24: =(K24-$E24)/K24 -> 0.10837438 | Q24: =(L24-$E24)/L24 -> 0.099502488
B25: Musculosa Bali | C25: Negra | D25: tank | E25: ='Precios Tab Dreamfull-sheets'!$G$12 -> 18100 | F25: 21800 | G25: =H25 -> 20800 | H25: 20800 | I25: 20700 | J25: 20500 | K25: 20300 | L25: 20100 | M25: =(H25-$E25)/H25 -> 0.12980769 | N25: =(I25-$E25)/I25 -> 0.12560386 | O25: =(J25-$E25)/J25 -> 0.11707317 | P25: =(K25-$E25)/K25 -> 0.10837438 | Q25: =(L25-$E25)/L25 -> 0.099502488

Sheet Precios_Partners_Growth
A1: Precios Partners GROWTH — cercanos a costo (+$1.000 base, escalón −$200/tier)
A2: PRECIO UNICO POR PRODUCTO (no por color): se calcula sobre el COSTO DEL COLOR MAS CARO + delta. Partner=+1000, Starter=+800, Pro=+600, Drop=+400, Bulk=+200. Garantiza min. 8% de ahorro vs el precio Partner normal. Recalcula automaticamente.
A4: Producto | B4: Color | C4: Categoria | D4: Costo | E4: Partner (1u) | F4: Starter (5-9u) | G4: Pro (10-20u) | H4: Drop (30-99u) | I4: Bulk (100+u) | J4: Margen%_Partner | K4: Margen%_Starter | L4: Margen%_Pro | M4: Margen%_Drop | N4: Margen%_Bulk
A5: =Precios_Para_Comunicar!B2 -> Buzo Cuello Redondo | B5: =Precios_Para_Comunicar!C2 -> Blanco | C5: =Precios_Para_Comunicar!D2 -> crewneck | D5: =Precios_Para_Comunicar!E2 -> 24100 | E5: =Resumen_por_Producto!$D$2+1000 -> 29170 | F5: =Resumen_por_Producto!$D$2+800 -> 28970 | G5: =Resumen_por_Producto!$D$2+600 -> 28770 | H5: =Resumen_por_Producto!$D$2+400 -> 28570 | I5: =Resumen_por_Producto!$D$2+200 -> 28370 | J5: =(E5-$D5)/E5 -> 0.17380871 | K5: =(F5-$D5)/F5 -> 0.16810494 | L5: =(G5-$D5)/G5 -> 0.16232186 | M5: =(H5-$D5)/H5 -> 0.15645782 | N5: =(I5-$D5)/I5 -> 0.1505111
A6: =Precios_Para_Comunicar!B3 -> Buzo Cuello Redondo | B6: =Precios_Para_Comunicar!C3 -> Negro | C6: =Precios_Para_Comunicar!D3 -> crewneck | D6: =Precios_Para_Comunicar!E3 -> 28170 | E6: =Resumen_por_Producto!$D$2+1000 -> 29170 | F6: =Resumen_por_Producto!$D$2+800 -> 28970 | G6: =Resumen_por_Producto!$D$2+600 -> 28770 | H6: =Resumen_por_Producto!$D$2+400 -> 28570 | I6: =Resumen_por_Producto!$D$2+200 -> 28370 | J6: =(E6-$D6)/E6 -> 0.034281796 | K6: =(F6-$D6)/F6 -> 0.027614774 | L6: =(G6-$D6)/G6 -> 0.020855057 | M6: =(H6-$D6)/H6 -> 0.0140007 | N6: =(I6-$D6)/I6 -> 0.0070497004
A7: =Precios_Para_Comunicar!B4 -> Buzo Cuello Redondo | B7: =Precios_Para_Comunicar!C4 -> Stone Wash | C7: =Precios_Para_Comunicar!D4 -> crewneck | D7: =Precios_Para_Comunicar!E4 -> 28170 | E7: =Resumen_por_Producto!$D$2+1000 -> 29170 | F7: =Resumen_por_Producto!$D$2+800 -> 28970 | G7: =Resumen_por_Producto!$D$2+600 -> 28770 | H7: =Resumen_por_Producto!$D$2+400 -> 28570 | I7: =Resumen_por_Producto!$D$2+200 -> 28370 | J7: =(E7-$D7)/E7 -> 0.034281796 | K7: =(F7-$D7)/F7 -> 0.027614774 | L7: =(G7-$D7)/G7 -> 0.020855057 | M7: =(H7-$D7)/H7 -> 0.0140007 | N7: =(I7-$D7)/I7 -> 0.0070497004
A8: =Precios_Para_Comunicar!B5 -> Buzo Hoodie Unisex | B8: =Precios_Para_Comunicar!C5 -> Blanco | C8: =Precios_Para_Comunicar!D5 -> hoodie | D8: =Precios_Para_Comunicar!E5 -> 25100 | E8: =Resumen_por_Producto!$D$3+1000 -> 31170 | F8: =Resumen_por_Producto!$D$3+800 -> 30970 | G8: =Resumen_por_Producto!$D$3+600 -> 30770 | H8: =Resumen_por_Producto!$D$3+400 -> 30570 | I8: =Resumen_por_Producto!$D$3+200 -> 30370 | J8: =(E8-$D8)/E8 -> 0.19473853 | K8: =(F8-$D8)/F8 -> 0.18953826 | L8: =(G8-$D8)/G8 -> 0.18427039 | M8: =(H8-$D8)/H8 -> 0.1789336 | N8: =(I8-$D8)/I8 -> 0.17352651
A9: =Precios_Para_Comunicar!B6 -> Buzo Hoodie Unisex | B9: =Precios_Para_Comunicar!C6 -> Negro | C9: =Precios_Para_Comunicar!D6 -> hoodie | D9: =Precios_Para_Comunicar!E6 -> 29170 | E9: =Resumen_por_Producto!$D$3+1000 -> 31170 | F9: =Resumen_por_Producto!$D$3+800 -> 30970 | G9: =Resumen_por_Producto!$D$3+600 -> 30770 | H9: =Resumen_por_Producto!$D$3+400 -> 30570 | I9: =Resumen_por_Producto!$D$3+200 -> 30370 | J9: =(E9-$D9)/E9 -> 0.064164261 | K9: =(F9-$D9)/F9 -> 0.058120762 | L9: =(G9-$D9)/G9 -> 0.0519987 | M9: =(H9-$D9)/H9 -> 0.045796533 | N9: =(I9-$D9)/I9 -> 0.039512677
A10: =Precios_Para_Comunicar!B7 -> Buzo Hoodie Unisex | B10: =Precios_Para_Comunicar!C7 -> Stone Wash | C10: =Precios_Para_Comunicar!D7 -> hoodie | D10: =Precios_Para_Comunicar!E7 -> 30170 | E10: =Resumen_por_Producto!$D$3+1000 -> 31170 | F10: =Resumen_por_Producto!$D$3+800 -> 30970 | G10: =Resumen_por_Producto!$D$3+600 -> 30770 | H10: =Resumen_por_Producto!$D$3+400 -> 30570 | I10: =Resumen_por_Producto!$D$3+200 -> 30370 | J10: =(E10-$D10)/E10 -> 0.03208213 | K10: =(F10-$D10)/F10 -> 0.02583145 | L10: =(G10-$D10)/G10 -> 0.019499513 | M10: =(H10-$D10)/H10 -> 0.013084724 | N10: =(I10-$D10)/I10 -> 0.0065854462
A11: =Precios_Para_Comunicar!B8 -> Buzo Hoodie Unisex | B11: =Precios_Para_Comunicar!C8 -> Caramel | C11: =Precios_Para_Comunicar!D8 -> hoodie | D11: =Precios_Para_Comunicar!E8 -> 29170 | E11: =Resumen_por_Producto!$D$3+1000 -> 31170 | F11: =Resumen_por_Producto!$D$3+800 -> 30970 | G11: =Resumen_por_Producto!$D$3+600 -> 30770 | H11: =Resumen_por_Producto!$D$3+400 -> 30570 | I11: =Resumen_por_Producto!$D$3+200 -> 30370 | J11: =(E11-$D11)/E11 -> 0.064164261 | K11: =(F11-$D11)/F11 -> 0.058120762 | L11: =(G11-$D11)/G11 -> 0.0519987 | M11: =(H11-$D11)/H11 -> 0.045796533 | N11: =(I11-$D11)/I11 -> 0.039512677
A12: =Precios_Para_Comunicar!B9 -> Buzo Hoodie Unisex | B12: =Precios_Para_Comunicar!C9 -> Crema | C12: =Precios_Para_Comunicar!D9 -> hoodie | D12: =Precios_Para_Comunicar!E9 -> 29170 | E12: =Resumen_por_Producto!$D$3+1000 -> 31170 | F12: =Resumen_por_Producto!$D$3+800 -> 30970 | G12: =Resumen_por_Producto!$D$3+600 -> 30770 | H12: =Resumen_por_Producto!$D$3+400 -> 30570 | I12: =Resumen_por_Producto!$D$3+200 -> 30370 | J12: =(E12-$D12)/E12 -> 0.064164261 | K12: =(F12-$D12)/F12 -> 0.058120762 | L12: =(G12-$D12)/G12 -> 0.0519987 | M12: =(H12-$D12)/H12 -> 0.045796533 | N12: =(I12-$D12)/I12 -> 0.039512677
A13: =Precios_Para_Comunicar!B10 -> Buzo Hoodie Unisex | B13: =Precios_Para_Comunicar!C10 -> Gris Melange | C13: =Precios_Para_Comunicar!D10 -> hoodie | D13: =Precios_Para_Comunicar!E10 -> 29170 | E13: =Resumen_por_Producto!$D$3+1000 -> 31170 | F13: =Resumen_por_Producto!$D$3+800 -> 30970 | G13: =Resumen_por_Producto!$D$3+600 -> 30770 | H13: =Resumen_por_Producto!$D$3+400 -> 30570 | I13: =Resumen_por_Producto!$D$3+200 -> 30370 | J13: =(E13-$D13)/E13 -> 0.064164261 | K13: =(F13-$D13)/F13 -> 0.058120762 | L13: =(G13-$D13)/G13 -> 0.0519987 | M13: =(H13-$D13)/H13 -> 0.045796533 | N13: =(I13-$D13)/I13 -> 0.039512677
A14: =Precios_Para_Comunicar!B11 -> Aura Oversize T-Shirt | B14: =Precios_Para_Comunicar!C11 -> Blanco | C14: =Precios_Para_Comunicar!D11 -> tee_oversize | D14: =Precios_Para_Comunicar!E11 -> 19000 | E14: =Resumen_por_Producto!$D$4+1000 -> 24470 | F14: =Resumen_por_Producto!$D$4+800 -> 24270 | G14: =Resumen_por_Producto!$D$4+600 -> 24070 | H14: =Resumen_por_Producto!$D$4+400 -> 23870 | I14: =Resumen_por_Producto!$D$4+200 -> 23670 | J14: =(E14-$D14)/E14 -> 0.22353903 | K14: =(F14-$D14)/F14 -> 0.2171405 | L14: =(G14-$D14)/G14 -> 0.21063565 | M14: =(H14-$D14)/H14 -> 0.20402178 | N14: =(I14-$D14)/I14 -> 0.19729616
A15: =Precios_Para_Comunicar!B12 -> Aura Oversize T-Shirt | B15: =Precios_Para_Comunicar!C12 -> Caramel | C15: =Precios_Para_Comunicar!D12 -> tee_oversize | D15: =Precios_Para_Comunicar!E12 -> 23070 | E15: =Resumen_por_Producto!$D$4+1000 -> 24470 | F15: =Resumen_por_Producto!$D$4+800 -> 24270 | G15: =Resumen_por_Producto!$D$4+600 -> 24070 | H15: =Resumen_por_Producto!$D$4+400 -> 23870 | I15: =Resumen_por_Producto!$D$4+200 -> 23670 | J15: =(E15-$D15)/E15 -> 0.057212914 | K15: =(F15-$D15)/F15 -> 0.049443758 | L15: =(G15-$D15)/G15 -> 0.041545492 | M15: =(H15-$D15)/H15 -> 0.033514872 | N15: =(I15-$D15)/I15 -> 0.025348542
A16: =Precios_Para_Comunicar!B13 -> Aura Oversize T-Shirt | B16: =Precios_Para_Comunicar!C13 -> Negro | C16: =Precios_Para_Comunicar!D13 -> tee_oversize | D16: =Precios_Para_Comunicar!E13 -> 23070 | E16: =Resumen_por_Producto!$D$4+1000 -> 24470 | F16: =Resumen_por_Producto!$D$4+800 -> 24270 | G16: =Resumen_por_Producto!$D$4+600 -> 24070 | H16: =Resumen_por_Producto!$D$4+400 -> 23870 | I16: =Resumen_por_Producto!$D$4+200 -> 23670 | J16: =(E16-$D16)/E16 -> 0.057212914 | K16: =(F16-$D16)/F16 -> 0.049443758 | L16: =(G16-$D16)/G16 -> 0.041545492 | M16: =(H16-$D16)/H16 -> 0.033514872 | N16: =(I16-$D16)/I16 -> 0.025348542
A17: =Precios_Para_Comunicar!B14 -> Aura Oversize T-Shirt | B17: =Precios_Para_Comunicar!C14 -> Stone Wash | C17: =Precios_Para_Comunicar!D14 -> tee_oversize | D17: =Precios_Para_Comunicar!E14 -> 23470 | E17: =Resumen_por_Producto!$D$4+1000 -> 24470 | F17: =Resumen_por_Producto!$D$4+800 -> 24270 | G17: =Resumen_por_Producto!$D$4+600 -> 24070 | H17: =Resumen_por_Producto!$D$4+400 -> 23870 | I17: =Resumen_por_Producto!$D$4+200 -> 23670 | J17: =(E17-$D17)/E17 -> 0.040866367 | K17: =(F17-$D17)/F17 -> 0.032962505 | L17: =(G17-$D17)/G17 -> 0.024927295 | M17: =(H17-$D17)/H17 -> 0.016757436 | N17: =(I17-$D17)/I17 -> 0.0084495142
A18: =Precios_Para_Comunicar!B15 -> Aldea Classic Fit T-Shirt | B18: =Precios_Para_Comunicar!C15 -> Blanco | C18: =Precios_Para_Comunicar!D15 -> tee_classic | D18: =Precios_Para_Comunicar!E15 -> 18600 | E18: =Resumen_por_Producto!$D$5+1000 -> 23670 | F18: =Resumen_por_Producto!$D$5+800 -> 23470 | G18: =Resumen_por_Producto!$D$5+600 -> 23270 | H18: =Resumen_por_Producto!$D$5+400 -> 23070 | I18: =Resumen_por_Producto!$D$5+200 -> 22870 | J18: =(E18-$D18)/E18 -> 0.21419518 | K18: =(F18-$D18)/F18 -> 0.20749893 | L18: =(G18-$D18)/G18 -> 0.20068758 | M18: =(H18-$D18)/H18 -> 0.19375813 | N18: =(I18-$D18)/I18 -> 0.18670748
A19: =Precios_Para_Comunicar!B16 -> Aldea Classic Fit T-Shirt | B19: =Precios_Para_Comunicar!C16 -> Negro | C19: =Precios_Para_Comunicar!D16 -> tee_classic | D19: =Precios_Para_Comunicar!E16 -> 22670 | E19: =Resumen_por_Producto!$D$5+1000 -> 23670 | F19: =Resumen_por_Producto!$D$5+800 -> 23470 | G19: =Resumen_por_Producto!$D$5+600 -> 23270 | H19: =Resumen_por_Producto!$D$5+400 -> 23070 | I19: =Resumen_por_Producto!$D$5+200 -> 22870 | J19: =(E19-$D19)/E19 -> 0.042247571 | K19: =(F19-$D19)/F19 -> 0.034086067 | L19: =(G19-$D19)/G19 -> 0.025784272 | M19: =(H19-$D19)/H19 -> 0.017338535 | N19: =(I19-$D19)/I19 -> 0.0087450809
A20: =Precios_Para_Comunicar!B17 -> Remera Clásica Mujer | B20: =Precios_Para_Comunicar!C17 -> Blanca | C20: =Precios_Para_Comunicar!D17 -> tee_classic | D20: =Precios_Para_Comunicar!E17 -> 18600 | E20: =Resumen_por_Producto!$D$6+1000 -> 23670 | F20: =Resumen_por_Producto!$D$6+800 -> 23470 | G20: =Resumen_por_Producto!$D$6+600 -> 23270 | H20: =Resumen_por_Producto!$D$6+400 -> 23070 | I20: =Resumen_por_Producto!$D$6+200 -> 22870 | J20: =(E20-$D20)/E20 -> 0.21419518 | K20: =(F20-$D20)/F20 -> 0.20749893 | L20: =(G20-$D20)/G20 -> 0.20068758 | M20: =(H20-$D20)/H20 -> 0.19375813 | N20: =(I20-$D20)/I20 -> 0.18670748
A21: =Precios_Para_Comunicar!B18 -> Remera Clásica Mujer | B21: =Precios_Para_Comunicar!C18 -> Negra | C21: =Precios_Para_Comunicar!D18 -> tee_classic | D21: =Precios_Para_Comunicar!E18 -> 22670 | E21: =Resumen_por_Producto!$D$6+1000 -> 23670 | F21: =Resumen_por_Producto!$D$6+800 -> 23470 | G21: =Resumen_por_Producto!$D$6+600 -> 23270 | H21: =Resumen_por_Producto!$D$6+400 -> 23070 | I21: =Resumen_por_Producto!$D$6+200 -> 22870 | J21: =(E21-$D21)/E21 -> 0.042247571 | K21: =(F21-$D21)/F21 -> 0.034086067 | L21: =(G21-$D21)/G21 -> 0.025784272 | M21: =(H21-$D21)/H21 -> 0.017338535 | N21: =(I21-$D21)/I21 -> 0.0087450809
A22: =Precios_Para_Comunicar!B19 -> Remera Crop Mujer | B22: =Precios_Para_Comunicar!C19 -> Amarillo | C22: =Precios_Para_Comunicar!D19 -> crop | D22: =Precios_Para_Comunicar!E19 -> 18100 | E22: =Resumen_por_Producto!$D$7+1000 -> 19100 | F22: =Resumen_por_Producto!$D$7+800 -> 18900 | G22: =Resumen_por_Producto!$D$7+600 -> 18700 | H22: =Resumen_por_Producto!$D$7+400 -> 18500 | I22: =Resumen_por_Producto!$D$7+200 -> 18300 | J22: =(E22-$D22)/E22 -> 0.052356021 | K22: =(F22-$D22)/F22 -> 0.042328042 | L22: =(G22-$D22)/G22 -> 0.032085561 | M22: =(H22-$D22)/H22 -> 0.021621622 | N22: =(I22-$D22)/I22 -> 0.010928962
A23: =Precios_Para_Comunicar!B20 -> Remera Crop Mujer | B23: =Precios_Para_Comunicar!C20 -> Chocolate | C23: =Precios_Para_Comunicar!D20 -> crop | D23: =Precios_Para_Comunicar!E20 -> 18100 | E23: =Resumen_por_Producto!$D$7+1000 -> 19100 | F23: =Resumen_por_Producto!$D$7+800 -> 18900 | G23: =Resumen_por_Producto!$D$7+600 -> 18700 | H23: =Resumen_por_Producto!$D$7+400 -> 18500 | I23: =Resumen_por_Producto!$D$7+200 -> 18300 | J23: =(E23-$D23)/E23 -> 0.052356021 | K23: =(F23-$D23)/F23 -> 0.042328042 | L23: =(G23-$D23)/G23 -> 0.032085561 | M23: =(H23-$D23)/H23 -> 0.021621622 | N23: =(I23-$D23)/I23 -> 0.010928962
A24: =Precios_Para_Comunicar!B21 -> Remera Crop Mujer | B24: =Precios_Para_Comunicar!C21 -> Gris Melange | C24: =Precios_Para_Comunicar!D21 -> crop | D24: =Precios_Para_Comunicar!E21 -> 18100 | E24: =Resumen_por_Producto!$D$7+1000 -> 19100 | F24: =Resumen_por_Producto!$D$7+800 -> 18900 | G24: =Resumen_por_Producto!$D$7+600 -> 18700 | H24: =Resumen_por_Producto!$D$7+400 -> 18500 | I24: =Resumen_por_Producto!$D$7+200 -> 18300 | J24: =(E24-$D24)/E24 -> 0.052356021 | K24: =(F24-$D24)/F24 -> 0.042328042 | L24: =(G24-$D24)/G24 -> 0.032085561 | M24: =(H24-$D24)/H24 -> 0.021621622 | N24: =(I24-$D24)/I24 -> 0.010928962
A25: =Precios_Para_Comunicar!B22 -> Remera Crop Mujer | B25: =Precios_Para_Comunicar!C22 -> Negra | C25: =Precios_Para_Comunicar!D22 -> crop | D25: =Precios_Para_Comunicar!E22 -> 18100 | E25: =Resumen_por_Producto!$D$7+1000 -> 19100 | F25: =Resumen_por_Producto!$D$7+800 -> 18900 | G25: =Resumen_por_Producto!$D$7+600 -> 18700 | H25: =Resumen_por_Producto!$D$7+400 -> 18500 | I25: =Resumen_por_Producto!$D$7+200 -> 18300 | J25: =(E25-$D25)/E25 -> 0.052356021 | K25: =(F25-$D25)/F25 -> 0.042328042 | L25: =(G25-$D25)/G25 -> 0.032085561 | M25: =(H25-$D25)/H25 -> 0.021621622 | N25: =(I25-$D25)/I25 -> 0.010928962
A26: =Precios_Para_Comunicar!B23 -> Musculosa Bali | B26: =Precios_Para_Comunicar!C23 -> Blanca | C26: =Precios_Para_Comunicar!D23 -> tank | D26: =Precios_Para_Comunicar!E23 -> 18100 | E26: =Resumen_por_Producto!$D$8+1000 -> 19100 | F26: =Resumen_por_Producto!$D$8+800 -> 18900 | G26: =Resumen_por_Producto!$D$8+600 -> 18700 | H26: =Resumen_por_Producto!$D$8+400 -> 18500 | I26: =Resumen_por_Producto!$D$8+200 -> 18300 | J26: =(E26-$D26)/E26 -> 0.052356021 | K26: =(F26-$D26)/F26 -> 0.042328042 | L26: =(G26-$D26)/G26 -> 0.032085561 | M26: =(H26-$D26)/H26 -> 0.021621622 | N26: =(I26-$D26)/I26 -> 0.010928962
A27: =Precios_Para_Comunicar!B24 -> Musculosa Bali | B27: =Precios_Para_Comunicar!C24 -> Gris | C27: =Precios_Para_Comunicar!D24 -> tank | D27: =Precios_Para_Comunicar!E24 -> 18100 | E27: =Resumen_por_Producto!$D$8+1000 -> 19100 | F27: =Resumen_por_Producto!$D$8+800 -> 18900 | G27: =Resumen_por_Producto!$D$8+600 -> 18700 | H27: =Resumen_por_Producto!$D$8+400 -> 18500 | I27: =Resumen_por_Producto!$D$8+200 -> 18300 | J27: =(E27-$D27)/E27 -> 0.052356021 | K27: =(F27-$D27)/F27 -> 0.042328042 | L27: =(G27-$D27)/G27 -> 0.032085561 | M27: =(H27-$D27)/H27 -> 0.021621622 | N27: =(I27-$D27)/I27 -> 0.010928962
A28: =Precios_Para_Comunicar!B25 -> Musculosa Bali | B28: =Precios_Para_Comunicar!C25 -> Negra | C28: =Precios_Para_Comunicar!D25 -> tank | D28: =Precios_Para_Comunicar!E25 -> 18100 | E28: =Resumen_por_Producto!$D$8+1000 -> 19100 | F28: =Resumen_por_Producto!$D$8+800 -> 18900 | G28: =Resumen_por_Producto!$D$8+600 -> 18700 | H28: =Resumen_por_Producto!$D$8+400 -> 18500 | I28: =Resumen_por_Producto!$D$8+200 -> 18300 | J28: =(E28-$D28)/E28 -> 0.052356021 | K28: =(F28-$D28)/F28 -> 0.042328042 | L28: =(G28-$D28)/G28 -> 0.032085561 | M28: =(H28-$D28)/H28 -> 0.021621622 | N28: =(I28-$D28)/I28 -> 0.010928962

Sheet Detalle_SKU_Con_Margenes
A1: Nombre_Comercial | B1: Producto | C1: Color | D1: Talle | E1: Categoria | F1: Costo | G1: B2C | H1: Muestra | I1: Partner (1u) | J1: Starter (5-9u) | K1: Pro (10-20u) | L1: Drop (30-99u) | M1: Bulk (100+u) | N1: $_Partner | O1: %_Partner | P1: $_Starter | Q1: %_Starter | R1: $_Pro | S1: %_Pro | T1: $_Drop | U1: %_Drop | V1: $_Bulk | W1: %_Bulk
A2: Berlin | B2: Buzo Cuello Redondo | C2: Blanco | D2: XS | E2: crewneck | F2: ='Precios Tab Dreamfull-sheets'!$G$2 -> 24100 | G2: 43000 | H2: 32200 | I2: 32200 | J2: 31200 | K2: 30200 | L2: 29200 | M2: 28200 | N2: =I2-$F2 -> 8100 | O2: =N2/I2 -> 0.2515528 | P2: =J2-$F2 -> 7100 | Q2: =P2/J2 -> 0.2275641 | R2: =K2-$F2 -> 6100 | S2: =R2/K2 -> 0.20198675 | T2: =L2-$F2 -> 5100 | U2: =T2/L2 -> 0.17465753 | V2: =M2-$F2 -> 4100 | W2: =V2/M2 -> 0.14539007
A3: Berlin | B3: Buzo Cuello Redondo | C3: Blanco | D3: S | E3: crewneck | F3: ='Precios Tab Dreamfull-sheets'!$G$2 -> 24100 | G3: 43000 | H3: 32200 | I3: 32200 | J3: 31200 | K3: 30200 | L3: 29200 | M3: 28200 | N3: =I3-$F3 -> 8100 | O3: =N3/I3 -> 0.2515528 | P3: =J3-$F3 -> 7100 | Q3: =P3/J3 -> 0.2275641 | R3: =K3-$F3 -> 6100 | S3: =R3/K3 -> 0.20198675 | T3: =L3-$F3 -> 5100 | U3: =T3/L3 -> 0.17465753 | V3: =M3-$F3 -> 4100 | W3: =V3/M3 -> 0.14539007
A4: Berlin | B4: Buzo Cuello Redondo | C4: Blanco | D4: M | E4: crewneck | F4: ='Precios Tab Dreamfull-sheets'!$G$2 -> 24100 | G4: 43000 | H4: 32200 | I4: 32200 | J4: 31200 | K4: 30200 | L4: 29200 | M4: 28200 | N4: =I4-$F4 -> 8100 | O4: =N4/I4 -> 0.2515528 | P4: =J4-$F4 -> 7100 | Q4: =P4/J4 -> 0.2275641 | R4: =K4-$F4 -> 6100 | S4: =R4/K4 -> 0.20198675 | T4: =L4-$F4 -> 5100 | U4: =T4/L4 -> 0.17465753 | V4: =M4-$F4 -> 4100 | W4: =V4/M4 -> 0.14539007
A5: Berlin | B5: Buzo Cuello Redondo | C5: Blanco | D5: L | E5: crewneck | F5: ='Precios Tab Dreamfull-sheets'!$G$2 -> 24100 | G5: 43000 | H5: 32200 | I5: 32200 | J5: 31200 | K5: 30200 | L5: 29200 | M5: 28200 | N5: =I5-$F5 -> 8100 | O5: =N5/I5 -> 0.2515528 | P5: =J5-$F5 -> 7100 | Q5: =P5/J5 -> 0.2275641 | R5: =K5-$F5 -> 6100 | S5: =R5/K5 -> 0.20198675 | T5: =L5-$F5 -> 5100 | U5: =T5/L5 -> 0.17465753 | V5: =M5-$F5 -> 4100 | W5: =V5/M5 -> 0.14539007
A6: Berlin | B6: Buzo Cuello Redondo | C6: Blanco | D6: XL | E6: crewneck | F6: ='Precios Tab Dreamfull-sheets'!$G$2 -> 24100 | G6: 43000 | H6: 32200 | I6: 32200 | J6: 31200 | K6: 30200 | L6: 29200 | M6: 28200 | N6: =I6-$F6 -> 8100 | O6: =N6/I6 -> 0.2515528 | P6: =J6-$F6 -> 7100 | Q6: =P6/J6 -> 0.2275641 | R6: =K6-$F6 -> 6100 | S6: =R6/K6 -> 0.20198675 | T6: =L6-$F6 -> 5100 | U6: =T6/L6 -> 0.17465753 | V6: =M6-$F6 -> 4100 | W6: =V6/M6 -> 0.14539007
A7: Berlin | B7: Buzo Cuello Redondo | C7: Blanco | D7: 2XL | E7: crewneck | F7: ='Precios Tab Dreamfull-sheets'!$G$2 -> 24100 | G7: 43000 | H7: 32200 | I7: 32200 | J7: 31200 | K7: 30200 | L7: 29200 | M7: 28200 | N7: =I7-$F7 -> 8100 | O7: =N7/I7 -> 0.2515528 | P7: =J7-$F7 -> 7100 | Q7: =P7/J7 -> 0.2275641 | R7: =K7-$F7 -> 6100 | S7: =R7/K7 -> 0.20198675 | T7: =L7-$F7 -> 5100 | U7: =T7/L7 -> 0.17465753 | V7: =M7-$F7 -> 4100 | W7: =V7/M7 -> 0.14539007
A8: Berlin | B8: Buzo Cuello Redondo | C8: Negro | D8: XS | E8: crewneck | F8: ='Precios Tab Dreamfull-sheets'!$G$3 -> 28170 | G8: 43000 | H8: 32200 | I8: 32200 | J8: 31200 | K8: 30200 | L8: 29200 | M8: 28200 | N8: =I8-$F8 -> 4030 | O8: =N8/I8 -> 0.12515528 | P8: =J8-$F8 -> 3030 | Q8: =P8/J8 -> 0.097115385 | R8: =K8-$F8 -> 2030 | S8: =R8/K8 -> 0.067218543 | T8: =L8-$F8 -> 1030 | U8: =T8/L8 -> 0.035273973 | V8: =M8-$F8 -> 30 | W8: =V8/M8 -> 0.0010638298
A9: Berlin | B9: Buzo Cuello Redondo | C9: Negro | D9: S | E9: crewneck | F9: ='Precios Tab Dreamfull-sheets'!$G$3 -> 28170 | G9: 43000 | H9: 32200 | I9: 32200 | J9: 31200 | K9: 30200 | L9: 29200 | M9: 28200 | N9: =I9-$F9 -> 4030 | O9: =N9/I9 -> 0.12515528 | P9: =J9-$F9 -> 3030 | Q9: =P9/J9 -> 0.097115385 | R9: =K9-$F9 -> 2030 | S9: =R9/K9 -> 0.067218543 | T9: =L9-$F9 -> 1030 | U9: =T9/L9 -> 0.035273973 | V9: =M9-$F9 -> 30 | W9: =V9/M9 -> 0.0010638298
A10: Berlin | B10: Buzo Cuello Redondo | C10: Negro | D10: M | E10: crewneck | F10: ='Precios Tab Dreamfull-sheets'!$G$3 -> 28170 | G10: 43000 | H10: 32200 | I10: 32200 | J10: 31200 | K10: 30200 | L10: 29200 | M10: 28200 | N10: =I10-$F10 -> 4030 | O10: =N10/I10 -> 0.12515528 | P10: =J10-$F10 -> 3030 | Q10: =P10/J10 -> 0.097115385 | R10: =K10-$F10 -> 2030 | S10: =R10/K10 -> 0.067218543 | T10: =L10-$F10 -> 1030 | U10: =T10/L10 -> 0.035273973 | V10: =M10-$F10 -> 30 | W10: =V10/M10 -> 0.0010638298
A11: Berlin | B11: Buzo Cuello Redondo | C11: Negro | D11: L | E11: crewneck | F11: ='Precios Tab Dreamfull-sheets'!$G$3 -> 28170 | G11: 43000 | H11: 32200 | I11: 32200 | J11: 31200 | K11: 30200 | L11: 29200 | M11: 28200 | N11: =I11-$F11 -> 4030 | O11: =N11/I11 -> 0.12515528 | P11: =J11-$F11 -> 3030 | Q11: =P11/J11 -> 0.097115385 | R11: =K11-$F11 -> 2030 | S11: =R11/K11 -> 0.067218543 | T11: =L11-$F11 -> 1030 | U11: =T11/L11 -> 0.035273973 | V11: =M11-$F11 -> 30 | W11: =V11/M11 -> 0.0010638298
A12: Berlin | B12: Buzo Cuello Redondo | C12: Negro | D12: XL | E12: crewneck | F12: ='Precios Tab Dreamfull-sheets'!$G$3 -> 28170 | G12: 43000 | H12: 32200 | I12: 32200 | J12: 31200 | K12: 30200 | L12: 29200 | M12: 28200 | N12: =I12-$F12 -> 4030 | O12: =N12/I12 -> 0.12515528 | P12: =J12-$F12 -> 3030 | Q12: =P12/J12 -> 0.097115385 | R12: =K12-$F12 -> 2030 | S12: =R12/K12 -> 0.067218543 | T12: =L12-$F12 -> 1030 | U12: =T12/L12 -> 0.035273973 | V12: =M12-$F12 -> 30 | W12: =V12/M12 -> 0.0010638298
A13: Berlin | B13: Buzo Cuello Redondo | C13: Negro | D13: 2XL | E13: crewneck | F13: ='Precios Tab Dreamfull-sheets'!$G$3 -> 28170 | G13: 43000 | H13: 32200 | I13: 32200 | J13: 31200 | K13: 30200 | L13: 29200 | M13: 28200 | N13: =I13-$F13 -> 4030 | O13: =N13/I13 -> 0.12515528 | P13: =J13-$F13 -> 3030 | Q13: =P13/J13 -> 0.097115385 | R13: =K13-$F13 -> 2030 | S13: =R13/K13 -> 0.067218543 | T13: =L13-$F13 -> 1030 | U13: =T13/L13 -> 0.035273973 | V13: =M13-$F13 -> 30 | W13: =V13/M13 -> 0.0010638298
A14: Berlin | B14: Buzo Cuello Redondo | C14: Stone Wash | D14: XS | E14: crewneck | F14: ='Precios Tab Dreamfull-sheets'!$G$4 -> 28170 | G14: 43000 | H14: 32200 | I14: 32200 | J14: 31200 | K14: 30200 | L14: 29200 | M14: 28200 | N14: =I14-$F14 -> 4030 | O14: =N14/I14 -> 0.12515528 | P14: =J14-$F14 -> 3030 | Q14: =P14/J14 -> 0.097115385 | R14: =K14-$F14 -> 2030 | S14: =R14/K14 -> 0.067218543 | T14: =L14-$F14 -> 1030 | U14: =T14/L14 -> 0.035273973 | V14: =M14-$F14 -> 30 | W14: =V14/M14 -> 0.0010638298
A15: Berlin | B15: Buzo Cuello Redondo | C15: Stone Wash | D15: S | E15: crewneck | F15: ='Precios Tab Dreamfull-sheets'!$G$4 -> 28170 | G15: 43000 | H15: 32200 | I15: 32200 | J15: 31200 | K15: 30200 | L15: 29200 | M15: 28200 | N15: =I15-$F15 -> 4030 | O15: =N15/I15 -> 0.12515528 | P15: =J15-$F15 -> 3030 | Q15: =P15/J15 -> 0.097115385 | R15: =K15-$F15 -> 2030 | S15: =R15/K15 -> 0.067218543 | T15: =L15-$F15 -> 1030 | U15: =T15/L15 -> 0.035273973 | V15: =M15-$F15 -> 30 | W15: =V15/M15 -> 0.0010638298
A16: Berlin | B16: Buzo Cuello Redondo | C16: Stone Wash | D16: M | E16: crewneck | F16: ='Precios Tab Dreamfull-sheets'!$G$4 -> 28170 | G16: 43000 | H16: 32200 | I16: 32200 | J16: 31200 | K16: 30200 | L16: 29200 | M16: 28200 | N16: =I16-$F16 -> 4030 | O16: =N16/I16 -> 0.12515528 | P16: =J16-$F16 -> 3030 | Q16: =P16/J16 -> 0.097115385 | R16: =K16-$F16 -> 2030 | S16: =R16/K16 -> 0.067218543 | T16: =L16-$F16 -> 1030 | U16: =T16/L16 -> 0.035273973 | V16: =M16-$F16 -> 30 | W16: =V16/M16 -> 0.0010638298
A17: Berlin | B17: Buzo Cuello Redondo | C17: Stone Wash | D17: L | E17: crewneck | F17: ='Precios Tab Dreamfull-sheets'!$G$4 -> 28170 | G17: 43000 | H17: 32200 | I17: 32200 | J17: 31200 | K17: 30200 | L17: 29200 | M17: 28200 | N17: =I17-$F17 -> 4030 | O17: =N17/I17 -> 0.12515528 | P17: =J17-$F17 -> 3030 | Q17: =P17/J17 -> 0.097115385 | R17: =K17-$F17 -> 2030 | S17: =R17/K17 -> 0.067218543 | T17: =L17-$F17 -> 1030 | U17: =T17/L17 -> 0.035273973 | V17: =M17-$F17 -> 30 | W17: =V17/M17 -> 0.0010638298
A18: Berlin | B18: Buzo Cuello Redondo | C18: Stone Wash | D18: XL | E18: crewneck | F18: ='Precios Tab Dreamfull-sheets'!$G$4 -> 28170 | G18: 43000 | H18: 32200 | I18: 32200 | J18: 31200 | K18: 30200 | L18: 29200 | M18: 28200 | N18: =I18-$F18 -> 4030 | O18: =N18/I18 -> 0.12515528 | P18: =J18-$F18 -> 3030 | Q18: =P18/J18 -> 0.097115385 | R18: =K18-$F18 -> 2030 | S18: =R18/K18 -> 0.067218543 | T18: =L18-$F18 -> 1030 | U18: =T18/L18 -> 0.035273973 | V18: =M18-$F18 -> 30 | W18: =V18/M18 -> 0.0010638298
A19: Berlin | B19: Buzo Cuello Redondo | C19: Stone Wash | D19: 2XL | E19: crewneck | F19: ='Precios Tab Dreamfull-sheets'!$G$4 -> 28170 | G19: 43000 | H19: 32200 | I19: 32200 | J19: 31200 | K19: 30200 | L19: 29200 | M19: 28200 | N19: =I19-$F19 -> 4030 | O19: =N19/I19 -> 0.12515528 | P19: =J19-$F19 -> 3030 | Q19: =P19/J19 -> 0.097115385 | R19: =K19-$F19 -> 2030 | S19: =R19/K19 -> 0.067218543 | T19: =L19-$F19 -> 1030 | U19: =T19/L19 -> 0.035273973 | V19: =M19-$F19 -> 30 | W19: =V19/M19 -> 0.0010638298
A20: Boston | B20: Buzo Hoodie Unisex | C20: Blanco | D20: XS | E20: hoodie | F20: ='Precios Tab Dreamfull-sheets'!$G$9 -> 25100 | G20: 55000 | H20: 38700 | I20: 38700 | J20: 36600 | K20: 34500 | L20: 32400 | M20: 30300 | N20: =I20-$F20 -> 13600 | O20: =N20/I20 -> 0.35142119 | P20: =J20-$F20 -> 11500 | Q20: =P20/J20 -> 0.31420765 | R20: =K20-$F20 -> 9400 | S20: =R20/K20 -> 0.27246377 | T20: =L20-$F20 -> 7300 | U20: =T20/L20 -> 0.22530864 | V20: =M20-$F20 -> 5200 | W20: =V20/M20 -> 0.17161716
A21: Boston | B21: Buzo Hoodie Unisex | C21: Blanco | D21: S | E21: hoodie | F21: ='Precios Tab Dreamfull-sheets'!$G$9 -> 25100 | G21: 55000 | H21: 38700 | I21: 38700 | J21: 36600 | K21: 34500 | L21: 32400 | M21: 30300 | N21: =I21-$F21 -> 13600 | O21: =N21/I21 -> 0.35142119 | P21: =J21-$F21 -> 11500 | Q21: =P21/J21 -> 0.31420765 | R21: =K21-$F21 -> 9400 | S21: =R21/K21 -> 0.27246377 | T21: =L21-$F21 -> 7300 | U21: =T21/L21 -> 0.22530864 | V21: =M21-$F21 -> 5200 | W21: =V21/M21 -> 0.17161716
A22: Boston | B22: Buzo Hoodie Unisex | C22: Blanco | D22: M | E22: hoodie | F22: ='Precios Tab Dreamfull-sheets'!$G$9 -> 25100 | G22: 55000 | H22: 38700 | I22: 38700 | J22: 36600 | K22: 34500 | L22: 32400 | M22: 30300 | N22: =I22-$F22 -> 13600 | O22: =N22/I22 -> 0.35142119 | P22: =J22-$F22 -> 11500 | Q22: =P22/J22 -> 0.31420765 | R22: =K22-$F22 -> 9400 | S22: =R22/K22 -> 0.27246377 | T22: =L22-$F22 -> 7300 | U22: =T22/L22 -> 0.22530864 | V22: =M22-$F22 -> 5200 | W22: =V22/M22 -> 0.17161716
A23: Boston | B23: Buzo Hoodie Unisex | C23: Blanco | D23: L | E23: hoodie | F23: ='Precios Tab Dreamfull-sheets'!$G$9 -> 25100 | G23: 55000 | H23: 38700 | I23: 38700 | J23: 36600 | K23: 34500 | L23: 32400 | M23: 30300 | N23: =I23-$F23 -> 13600 | O23: =N23/I23 -> 0.35142119 | P23: =J23-$F23 -> 11500 | Q23: =P23/J23 -> 0.31420765 | R23: =K23-$F23 -> 9400 | S23: =R23/K23 -> 0.27246377 | T23: =L23-$F23 -> 7300 | U23: =T23/L23 -> 0.22530864 | V23: =M23-$F23 -> 5200 | W23: =V23/M23 -> 0.17161716
A24: Boston | B24: Buzo Hoodie Unisex | C24: Blanco | D24: XL | E24: hoodie | F24: ='Precios Tab Dreamfull-sheets'!$G$9 -> 25100 | G24: 55000 | H24: 38700 | I24: 38700 | J24: 36600 | K24: 34500 | L24: 32400 | M24: 30300 | N24: =I24-$F24 -> 13600 | O24: =N24/I24 -> 0.35142119 | P24: =J24-$F24 -> 11500 | Q24: =P24/J24 -> 0.31420765 | R24: =K24-$F24 -> 9400 | S24: =R24/K24 -> 0.27246377 | T24: =L24-$F24 -> 7300 | U24: =T24/L24 -> 0.22530864 | V24: =M24-$F24 -> 5200 | W24: =V24/M24 -> 0.17161716
A25: Boston | B25: Buzo Hoodie Unisex | C25: Blanco | D25: 2XL | E25: hoodie | F25: ='Precios Tab Dreamfull-sheets'!$G$9 -> 25100 | G25: 55000 | H25: 38700 | I25: 38700 | J25: 36600 | K25: 34500 | L25: 32400 | M25: 30300 | N25: =I25-$F25 -> 13600 | O25: =N25/I25 -> 0.35142119 | P25: =J25-$F25 -> 11500 | Q25: =P25/J25 -> 0.31420765 | R25: =K25-$F25 -> 9400 | S25: =R25/K25 -> 0.27246377 | T25: =L25-$F25 -> 7300 | U25: =T25/L25 -> 0.22530864 | V25: =M25-$F25 -> 5200 | W25: =V25/M25 -> 0.17161716
A26: Boston | B26: Buzo Hoodie Unisex | C26: Negro | D26: XS | E26: hoodie | F26: ='Precios Tab Dreamfull-sheets'!$G$10 -> 29170 | G26: 55000 | H26: 38700 | I26: 38700 | J26: 36600 | K26: 34500 | L26: 32400 | M26: 30300 | N26: =I26-$F26 -> 9530 | O26: =N26/I26 -> 0.24625323 | P26: =J26-$F26 -> 7430 | Q26: =P26/J26 -> 0.20300546 | R26: =K26-$F26 -> 5330 | S26: =R26/K26 -> 0.15449275 | T26: =L26-$F26 -> 3230 | U26: =T26/L26 -> 0.099691358 | V26: =M26-$F26 -> 1130 | W26: =V26/M26 -> 0.037293729
A27: Boston | B27: Buzo Hoodie Unisex | C27: Negro | D27: S | E27: hoodie | F27: ='Precios Tab Dreamfull-sheets'!$G$10 -> 29170 | G27: 55000 | H27: 38700 | I27: 38700 | J27: 36600 | K27: 34500 | L27: 32400 | M27: 30300 | N27: =I27-$F27 -> 9530 | O27: =N27/I27 -> 0.24625323 | P27: =J27-$F27 -> 7430 | Q27: =P27/J27 -> 0.20300546 | R27: =K27-$F27 -> 5330 | S27: =R27/K27 -> 0.15449275 | T27: =L27-$F27 -> 3230 | U27: =T27/L27 -> 0.099691358 | V27: =M27-$F27 -> 1130 | W27: =V27/M27 -> 0.037293729
A28: Boston | B28: Buzo Hoodie Unisex | C28: Negro | D28: M | E28: hoodie | F28: ='Precios Tab Dreamfull-sheets'!$G$10 -> 29170 | G28: 55000 | H28: 38700 | I28: 38700 | J28: 36600 | K28: 34500 | L28: 32400 | M28: 30300 | N28: =I28-$F28 -> 9530 | O28: =N28/I28 -> 0.24625323 | P28: =J28-$F28 -> 7430 | Q28: =P28/J28 -> 0.20300546 | R28: =K28-$F28 -> 5330 | S28: =R28/K28 -> 0.15449275 | T28: =L28-$F28 -> 3230 | U28: =T28/L28 -> 0.099691358 | V28: =M28-$F28 -> 1130 | W28: =V28/M28 -> 0.037293729
A29: Boston | B29: Buzo Hoodie Unisex | C29: Negro | D29: L | E29: hoodie | F29: ='Precios Tab Dreamfull-sheets'!$G$10 -> 29170 | G29: 55000 | H29: 38700 | I29: 38700 | J29: 36600 | K29: 34500 | L29: 32400 | M29: 30300 | N29: =I29-$F29 -> 9530 | O29: =N29/I29 -> 0.24625323 | P29: =J29-$F29 -> 7430 | Q29: =P29/J29 -> 0.20300546 | R29: =K29-$F29 -> 5330 | S29: =R29/K29 -> 0.15449275 | T29: =L29-$F29 -> 3230 | U29: =T29/L29 -> 0.099691358 | V29: =M29-$F29 -> 1130 | W29: =V29/M29 -> 0.037293729
A30: Boston | B30: Buzo Hoodie Unisex | C30: Negro | D30: XL | E30: hoodie | F30: ='Precios Tab Dreamfull-sheets'!$G$10 -> 29170 | G30: 55000 | H30: 38700 | I30: 38700 | J30: 36600 | K30: 34500 | L30: 32400 | M30: 30300 | N30: =I30-$F30 -> 9530 | O30: =N30/I30 -> 0.24625323 | P30: =J30-$F30 -> 7430 | Q30: =P30/J30 -> 0.20300546 | R30: =K30-$F30 -> 5330 | S30: =R30/K30 -> 0.15449275 | T30: =L30-$F30 -> 3230 | U30: =T30/L30 -> 0.099691358 | V30: =M30-$F30 -> 1130 | W30: =V30/M30 -> 0.037293729
A31: Boston | B31: Buzo Hoodie Unisex | C31: Negro | D31: 2XL | E31: hoodie | F31: ='Precios Tab Dreamfull-sheets'!$G$10 -> 29170 | G31: 55000 | H31: 38700 | I31: 38700 | J31: 36600 | K31: 34500 | L31: 32400 | M31: 30300 | N31: =I31-$F31 -> 9530 | O31: =N31/I31 -> 0.24625323 | P31: =J31-$F31 -> 7430 | Q31: =P31/J31 -> 0.20300546 | R31: =K31-$F31 -> 5330 | S31: =R31/K31 -> 0.15449275 | T31: =L31-$F31 -> 3230 | U31: =T31/L31 -> 0.099691358 | V31: =M31-$F31 -> 1130 | W31: =V31/M31 -> 0.037293729
A32: Boston | B32: Buzo Hoodie Unisex | C32: Stone Wash | D32: XS | E32: hoodie | F32: ='Precios Tab Dreamfull-sheets'!$G$11 -> 30170 | G32: 55000 | H32: 38700 | I32: 38700 | J32: 36600 | K32: 34500 | L32: 32400 | M32: 30300 | N32: =I32-$F32 -> 8530 | O32: =N32/I32 -> 0.22041344 | P32: =J32-$F32 -> 6430 | Q32: =P32/J32 -> 0.17568306 | R32: =K32-$F32 -> 4330 | S32: =R32/K32 -> 0.12550725 | T32: =L32-$F32 -> 2230 | U32: =T32/L32 -> 0.06882716 | V32: =M32-$F32 -> 130 | W32: =V32/M32 -> 0.004290429
A33: Boston | B33: Buzo Hoodie Unisex | C33: Stone Wash | D33: S | E33: hoodie | F33: ='Precios Tab Dreamfull-sheets'!$G$11 -> 30170 | G33: 55000 | H33: 38700 | I33: 38700 | J33: 36600 | K33: 34500 | L33: 32400 | M33: 30300 | N33: =I33-$F33 -> 8530 | O33: =N33/I33 -> 0.22041344 | P33: =J33-$F33 -> 6430 | Q33: =P33/J33 -> 0.17568306 | R33: =K33-$F33 -> 4330 | S33: =R33/K33 -> 0.12550725 | T33: =L33-$F33 -> 2230 | U33: =T33/L33 -> 0.06882716 | V33: =M33-$F33 -> 130 | W33: =V33/M33 -> 0.004290429
A34: Boston | B34: Buzo Hoodie Unisex | C34: Stone Wash | D34: M | E34: hoodie | F34: ='Precios Tab Dreamfull-sheets'!$G$11 -> 30170 | G34: 55000 | H34: 38700 | I34: 38700 | J34: 36600 | K34: 34500 | L34: 32400 | M34: 30300 | N34: =I34-$F34 -> 8530 | O34: =N34/I34 -> 0.22041344 | P34: =J34-$F34 -> 6430 | Q34: =P34/J34 -> 0.17568306 | R34: =K34-$F34 -> 4330 | S34: =R34/K34 -> 0.12550725 | T34: =L34-$F34 -> 2230 | U34: =T34/L34 -> 0.06882716 | V34: =M34-$F34 -> 130 | W34: =V34/M34 -> 0.004290429
A35: Boston | B35: Buzo Hoodie Unisex | C35: Stone Wash | D35: L | E35: hoodie | F35: ='Precios Tab Dreamfull-sheets'!$G$11 -> 30170 | G35: 55000 | H35: 38700 | I35: 38700 | J35: 36600 | K35: 34500 | L35: 32400 | M35: 30300 | N35: =I35-$F35 -> 8530 | O35: =N35/I35 -> 0.22041344 | P35: =J35-$F35 -> 6430 | Q35: =P35/J35 -> 0.17568306 | R35: =K35-$F35 -> 4330 | S35: =R35/K35 -> 0.12550725 | T35: =L35-$F35 -> 2230 | U35: =T35/L35 -> 0.06882716 | V35: =M35-$F35 -> 130 | W35: =V35/M35 -> 0.004290429
A36: Boston | B36: Buzo Hoodie Unisex | C36: Stone Wash | D36: XL | E36: hoodie | F36: ='Precios Tab Dreamfull-sheets'!$G$11 -> 30170 | G36: 55000 | H36: 38700 | I36: 38700 | J36: 36600 | K36: 34500 | L36: 32400 | M36: 30300 | N36: =I36-$F36 -> 8530 | O36: =N36/I36 -> 0.22041344 | P36: =J36-$F36 -> 6430 | Q36: =P36/J36 -> 0.17568306 | R36: =K36-$F36 -> 4330 | S36: =R36/K36 -> 0.12550725 | T36: =L36-$F36 -> 2230 | U36: =T36/L36 -> 0.06882716 | V36: =M36-$F36 -> 130 | W36: =V36/M36 -> 0.004290429
A37: Boston | B37: Buzo Hoodie Unisex | C37: Stone Wash | D37: 2XL | E37: hoodie | F37: ='Precios Tab Dreamfull-sheets'!$G$11 -> 30170 | G37: 55000 | H37: 38700 | I37: 38700 | J37: 36600 | K37: 34500 | L37: 32400 | M37: 30300 | N37: =I37-$F37 -> 8530 | O37: =N37/I37 -> 0.22041344 | P37: =J37-$F37 -> 6430 | Q37: =P37/J37 -> 0.17568306 | R37: =K37-$F37 -> 4330 | S37: =R37/K37 -> 0.12550725 | T37: =L37-$F37 -> 2230 | U37: =T37/L37 -> 0.06882716 | V37: =M37-$F37 -> 130 | W37: =V37/M37 -> 0.004290429
A38: Boston | B38: Buzo Hoodie Unisex | C38: Caramel | D38: S | E38: hoodie | F38: ='Precios Tab Dreamfull-sheets'!$G$10 -> 29170 | G38: 55000 | H38: 38700 | I38: 38700 | J38: 36600 | K38: 34500 | L38: 32400 | M38: 30300 | N38: =I38-$F38 -> 9530 | O38: =N38/I38 -> 0.24625323 | P38: =J38-$F38 -> 7430 | Q38: =P38/J38 -> 0.20300546 | R38: =K38-$F38 -> 5330 | S38: =R38/K38 -> 0.15449275 | T38: =L38-$F38 -> 3230 | U38: =T38/L38 -> 0.099691358 | V38: =M38-$F38 -> 1130 | W38: =V38/M38 -> 0.037293729
A39: Boston | B39: Buzo Hoodie Unisex | C39: Caramel | D39: M | E39: hoodie | F39: ='Precios Tab Dreamfull-sheets'!$G$10 -> 29170 | G39: 55000 | H39: 38700 | I39: 38700 | J39: 36600 | K39: 34500 | L39: 32400 | M39: 30300 | N39: =I39-$F39 -> 9530 | O39: =N39/I39 -> 0.24625323 | P39: =J39-$F39 -> 7430 | Q39: =P39/J39 -> 0.20300546 | R39: =K39-$F39 -> 5330 | S39: =R39/K39 -> 0.15449275 | T39: =L39-$F39 -> 3230 | U39: =T39/L39 -> 0.099691358 | V39: =M39-$F39 -> 1130 | W39: =V39/M39 -> 0.037293729
A40: Boston | B40: Buzo Hoodie Unisex | C40: Caramel | D40: L | E40: hoodie | F40: ='Precios Tab Dreamfull-sheets'!$G$10 -> 29170 | G40: 55000 | H40: 38700 | I40: 38700 | J40: 36600 | K40: 34500 | L40: 32400 | M40: 30300 | N40: =I40-$F40 -> 9530 | O40: =N40/I40 -> 0.24625323 | P40: =J40-$F40 -> 7430 | Q40: =P40/J40 -> 0.20300546 | R40: =K40-$F40 -> 5330 | S40: =R40/K40 -> 0.15449275 | T40: =L40-$F40 -> 3230 | U40: =T40/L40 -> 0.099691358 | V40: =M40-$F40 -> 1130 | W40: =V40/M40 -> 0.037293729
A41: Boston | B41: Buzo Hoodie Unisex | C41: Caramel | D41: XL | E41: hoodie | F41: ='Precios Tab Dreamfull-sheets'!$G$10 -> 29170 | G41: 55000 | H41: 38700 | I41: 38700 | J41: 36600 | K41: 34500 | L41: 32400 | M41: 30300 | N41: =I41-$F41 -> 9530 | O41: =N41/I41 -> 0.24625323 | P41: =J41-$F41 -> 7430 | Q41: =P41/J41 -> 0.20300546 | R41: =K41-$F41 -> 5330 | S41: =R41/K41 -> 0.15449275 | T41: =L41-$F41 -> 3230 | U41: =T41/L41 -> 0.099691358 | V41: =M41-$F41 -> 1130 | W41: =V41/M41 -> 0.037293729
A42: Boston | B42: Buzo Hoodie Unisex | C42: Caramel | D42: XXL | E42: hoodie | F42: ='Precios Tab Dreamfull-sheets'!$G$10 -> 29170 | G42: 55000 | H42: 38700 | I42: 38700 | J42: 36600 | K42: 34500 | L42: 32400 | M42: 30300 | N42: =I42-$F42 -> 9530 | O42: =N42/I42 -> 0.24625323 | P42: =J42-$F42 -> 7430 | Q42: =P42/J42 -> 0.20300546 | R42: =K42-$F42 -> 5330 | S42: =R42/K42 -> 0.15449275 | T42: =L42-$F42 -> 3230 | U42: =T42/L42 -> 0.099691358 | V42: =M42-$F42 -> 1130 | W42: =V42/M42 -> 0.037293729
A43: Boston | B43: Buzo Hoodie Unisex | C43: Crema | D43: S | E43: hoodie | F43: ='Precios Tab Dreamfull-sheets'!$G$10 -> 29170 | G43: 55000 | H43: 38700 | I43: 38700 | J43: 36600 | K43: 34500 | L43: 32400 | M43: 30300 | N43: =I43-$F43 -> 9530 | O43: =N43/I43 -> 0.24625323 | P43: =J43-$F43 -> 7430 | Q43: =P43/J43 -> 0.20300546 | R43: =K43-$F43 -> 5330 | S43: =R43/K43 -> 0.15449275 | T43: =L43-$F43 -> 3230 | U43: =T43/L43 -> 0.099691358 | V43: =M43-$F43 -> 1130 | W43: =V43/M43 -> 0.037293729
A44: Boston | B44: Buzo Hoodie Unisex | C44: Crema | D44: M | E44: hoodie | F44: ='Precios Tab Dreamfull-sheets'!$G$10 -> 29170 | G44: 55000 | H44: 38700 | I44: 38700 | J44: 36600 | K44: 34500 | L44: 32400 | M44: 30300 | N44: =I44-$F44 -> 9530 | O44: =N44/I44 -> 0.24625323 | P44: =J44-$F44 -> 7430 | Q44: =P44/J44 -> 0.20300546 | R44: =K44-$F44 -> 5330 | S44: =R44/K44 -> 0.15449275 | T44: =L44-$F44 -> 3230 | U44: =T44/L44 -> 0.099691358 | V44: =M44-$F44 -> 1130 | W44: =V44/M44 -> 0.037293729
A45: Boston | B45: Buzo Hoodie Unisex | C45: Crema | D45: L | E45: hoodie | F45: ='Precios Tab Dreamfull-sheets'!$G$10 -> 29170 | G45: 55000 | H45: 38700 | I45: 38700 | J45: 36600 | K45: 34500 | L45: 32400 | M45: 30300 | N45: =I45-$F45 -> 9530 | O45: =N45/I45 -> 0.24625323 | P45: =J45-$F45 -> 7430 | Q45: =P45/J45 -> 0.20300546 | R45: =K45-$F45 -> 5330 | S45: =R45/K45 -> 0.15449275 | T45: =L45-$F45 -> 3230 | U45: =T45/L45 -> 0.099691358 | V45: =M45-$F45 -> 1130 | W45: =V45/M45 -> 0.037293729
A46: Boston | B46: Buzo Hoodie Unisex | C46: Crema | D46: XL | E46: hoodie | F46: ='Precios Tab Dreamfull-sheets'!$G$10 -> 29170 | G46: 55000 | H46: 38700 | I46: 38700 | J46: 36600 | K46: 34500 | L46: 32400 | M46: 30300 | N46: =I46-$F46 -> 9530 | O46: =N46/I46 -> 0.24625323 | P46: =J46-$F46 -> 7430 | Q46: =P46/J46 -> 0.20300546 | R46: =K46-$F46 -> 5330 | S46: =R46/K46 -> 0.15449275 | T46: =L46-$F46 -> 3230 | U46: =T46/L46 -> 0.099691358 | V46: =M46-$F46 -> 1130 | W46: =V46/M46 -> 0.037293729
A47: Boston | B47: Buzo Hoodie Unisex | C47: Crema | D47: XXL | E47: hoodie | F47: ='Precios Tab Dreamfull-sheets'!$G$10 -> 29170 | G47: 55000 | H47: 38700 | I47: 38700 | J47: 36600 | K47: 34500 | L47: 32400 | M47: 30300 | N47: =I47-$F47 -> 9530 | O47: =N47/I47 -> 0.24625323 | P47: =J47-$F47 -> 7430 | Q47: =P47/J47 -> 0.20300546 | R47: =K47-$F47 -> 5330 | S47: =R47/K47 -> 0.15449275 | T47: =L47-$F47 -> 3230 | U47: =T47/L47 -> 0.099691358 | V47: =M47-$F47 -> 1130 | W47: =V47/M47 -> 0.037293729
A48: Boston | B48: Buzo Hoodie Unisex | C48: Gris Melange | D48: S | E48: hoodie | F48: ='Precios Tab Dreamfull-sheets'!$G$10 -> 29170 | G48: 55000 | H48: 38700 | I48: 38700 | J48: 36600 | K48: 34500 | L48: 32400 | M48: 30300 | N48: =I48-$F48 -> 9530 | O48: =N48/I48 -> 0.24625323 | P48: =J48-$F48 -> 7430 | Q48: =P48/J48 -> 0.20300546 | R48: =K48-$F48 -> 5330 | S48: =R48/K48 -> 0.15449275 | T48: =L48-$F48 -> 3230 | U48: =T48/L48 -> 0.099691358 | V48: =M48-$F48 -> 1130 | W48: =V48/M48 -> 0.037293729
A49: Boston | B49: Buzo Hoodie Unisex | C49: Gris Melange | D49: M | E49: hoodie | F49: ='Precios Tab Dreamfull-sheets'!$G$10 -> 29170 | G49: 55000 | H49: 38700 | I49: 38700 | J49: 36600 | K49: 34500 | L49: 32400 | M49: 30300 | N49: =I49-$F49 -> 9530 | O49: =N49/I49 -> 0.24625323 | P49: =J49-$F49 -> 7430 | Q49: =P49/J49 -> 0.20300546 | R49: =K49-$F49 -> 5330 | S49: =R49/K49 -> 0.15449275 | T49: =L49-$F49 -> 3230 | U49: =T49/L49 -> 0.099691358 | V49: =M49-$F49 -> 1130 | W49: =V49/M49 -> 0.037293729
... A52: Boston | B52: Buzo Hoodie Unisex | C52: Gris Melange | D52: XXL | E52: hoodie | F52: ='Precios Tab Dreamfull-sheets'!$G$10 -> 29170 | G52: 55000 | H52: 38700 | I52: 38700 | J52: 36600 | K52: 34500 | L52: 32400 | M52: 30300 | N52: =I52-$F52 -> 9530 | O52: =N52/I52 -> 0.24625323 | P52: =J52-$F52 -> 7430 | Q52: =P52/J52 -> 0.20300546 | R52: =K52-$F52 -> 5330 | S52: =R52/K52 -> 0.15449275 | T52: =L52-$F52 -> 3230 | U52: =T52/L52 -> 0.099691358 | V52: =M52-$F52 -> 1130 | W52: =V52/M52 -> 0.037293729
A53: Aura | B53: Aura Oversize T-Shirt | C53: Blanco | D53: 2XS | E53: tee_oversize | F53: ='Precios Tab Dreamfull-sheets'!$G$18 -> 19000 | G53: 31000 | H53: 25400 | I53: 25400 | J53: 24700 | K53: 24000 | L53: 23200 | M53: 22500 | N53: =I53-$F53 -> 6400 | O53: =N53/I53 -> 0.2519685 | P53: =J53-$F53 -> 5700 | Q53: =P53/J53 -> 0.23076923 | R53: =K53-$F53 -> 5000 | S53: =R53/K53 -> 0.20833333 | T53: =L53-$F53 -> 4200 | U53: =T53/L53 -> 0.18103448 | V53: =M53-$F53 -> 3500 | W53: =V53/M53 -> 0.15555556
A54: Aura | B54: Aura Oversize T-Shirt | C54: Blanco | D54: XS | E54: tee_oversize | F54: ='Precios Tab Dreamfull-sheets'!$G$18 -> 19000 | G54: 31000 | H54: 25400 | I54: 25400 | J54: 24700 | K54: 24000 | L54: 23200 | M54: 22500 | N54: =I54-$F54 -> 6400 | O54: =N54/I54 -> 0.2519685 | P54: =J54-$F54 -> 5700 | Q54: =P54/J54 -> 0.23076923 | R54: =K54-$F54 -> 5000 | S54: =R54/K54 -> 0.20833333 | T54: =L54-$F54 -> 4200 | U54: =T54/L54 -> 0.18103448 | V54: =M54-$F54 -> 3500 | W54: =V54/M54 -> 0.15555556
A55: Aura | B55: Aura Oversize T-Shirt | C55: Blanco | D55: S | E55: tee_oversize | F55: ='Precios Tab Dreamfull-sheets'!$G$18 -> 19000 | G55: 31000 | H55: 25400 | I55: 25400 | J55: 24700 | K55: 24000 | L55: 23200 | M55: 22500 | N55: =I55-$F55 -> 6400 | O55: =N55/I55 -> 0.2519685 | P55: =J55-$F55 -> 5700 | Q55: =P55/J55 -> 0.23076923 | R55: =K55-$F55 -> 5000 | S55: =R55/K55 -> 0.20833333 | T55: =L55-$F55 -> 4200 | U55: =T55/L55 -> 0.18103448 | V55: =M55-$F55 -> 3500 | W55: =V55/M55 -> 0.15555556
A56: Aura | B56: Aura Oversize T-Shirt | C56: Blanco | D56: M | E56: tee_oversize | F56: ='Precios Tab Dreamfull-sheets'!$G$18 -> 19000 | G56: 31000 | H56: 25400 | I56: 25400 | J56: 24700 | K56: 24000 | L56: 23200 | M56: 22500 | N56: =I56-$F56 -> 6400 | O56: =N56/I56 -> 0.2519685 | P56: =J56-$F56 -> 5700 | Q56: =P56/J56 -> 0.23076923 | R56: =K56-$F56 -> 5000 | S56: =R56/K56 -> 0.20833333 | T56: =L56-$F56 -> 4200 | U56: =T56/L56 -> 0.18103448 | V56: =M56-$F56 -> 3500 | W56: =V56/M56 -> 0.15555556
A57: Aura | B57: Aura Oversize T-Shirt | C57: Blanco | D57: L | E57: tee_oversize | F57: ='Precios Tab Dreamfull-sheets'!$G$18 -> 19000 | G57: 31000 | H57: 25400 | I57: 25400 | J57: 24700 | K57: 24000 | L57: 23200 | M57: 22500 | N57: =I57-$F57 -> 6400 | O57: =N57/I57 -> 0.2519685 | P57: =J57-$F57 -> 5700 | Q57: =P57/J57 -> 0.23076923 | R57: =K57-$F57 -> 5000 | S57: =R57/K57 -> 0.20833333 | T57: =L57-$F57 -> 4200 | U57: =T57/L57 -> 0.18103448 | V57: =M57-$F57 -> 3500 | W57: =V57/M57 -> 0.15555556
A58: Aura | B58: Aura Oversize T-Shirt | C58: Blanco | D58: XL | E58: tee_oversize | F58: ='Precios Tab Dreamfull-sheets'!$G$18 -> 19000 | G58: 31000 | H58: 25400 | I58: 25400 | J58: 24700 | K58: 24000 | L58: 23200 | M58: 22500 | N58: =I58-$F58 -> 6400 | O58: =N58/I58 -> 0.2519685 | P58: =J58-$F58 -> 5700 | Q58: =P58/J58 -> 0.23076923 | R58: =K58-$F58 -> 5000 | S58: =R58/K58 -> 0.20833333 | T58: =L58-$F58 -> 4200 | U58: =T58/L58 -> 0.18103448 | V58: =M58-$F58 -> 3500 | W58: =V58/M58 -> 0.15555556
A59: Aura | B59: Aura Oversize T-Shirt | C59: Blanco | D59: 2XL | E59: tee_oversize | F59: ='Precios Tab Dreamfull-sheets'!$G$18 -> 19000 | G59: 31000 | H59: 25400 | I59: 25400 | J59: 24700 | K59: 24000 | L59: 23200 | M59: 22500 | N59: =I59-$F59 -> 6400 | O59: =N59/I59 -> 0.2519685 | P59: =J59-$F59 -> 5700 | Q59: =P59/J59 -> 0.23076923 | R59: =K59-$F59 -> 5000 | S59: =R59/K59 -> 0.20833333 | T59: =L59-$F59 -> 4200 | U59: =T59/L59 -> 0.18103448 | V59: =M59-$F59 -> 3500 | W59: =V59/M59 -> 0.15555556
A60: Aura | B60: Aura Oversize T-Shirt | C60: Caramel | D60: S | E60: tee_oversize | F60: ='Precios Tab Dreamfull-sheets'!$G$19 -> 23070 | G60: 31000 | H60: 25400 | I60: 25400 | J60: 24700 | K60: 24000 | L60: 23200 | M60: =ROUND($F60*1.04,-2) -> 24000 | N60: =I60-$F60 -> 2330 | O60: =N60/I60 -> 0.091732283 | P60: =J60-$F60 -> 1630 | Q60: =P60/J60 -> 0.065991903 | R60: =K60-$F60 -> 930 | S60: =R60/K60 -> 0.03875 | T60: =L60-$F60 -> 130 | U60: =T60/L60 -> 0.0056034483 | V60: =M60-$F60 -> 930 | W60: =V60/M60 -> 0.03875
A61: Aura | B61: Aura Oversize T-Shirt | C61: Caramel | D61: M | E61: tee_oversize | F61: ='Precios Tab Dreamfull-sheets'!$G$19 -> 23070 | G61: 31000 | H61: 25400 | I61: 25400 | J61: 24700 | K61: 24000 | L61: 23200 | M61: =ROUND($F61*1.04,-2) -> 24000 | N61: =I61-$F61 -> 2330 | O61: =N61/I61 -> 0.091732283 | P61: =J61-$F61 -> 1630 | Q61: =P61/J61 -> 0.065991903 | R61: =K61-$F61 -> 930 | S61: =R61/K61 -> 0.03875 | T61: =L61-$F61 -> 130 | U61: =T61/L61 -> 0.0056034483 | V61: =M61-$F61 -> 930 | W61: =V61/M61 -> 0.03875
A62: Aura | B62: Aura Oversize T-Shirt | C62: Caramel | D62: L | E62: tee_oversize | F62: ='Precios Tab Dreamfull-sheets'!$G$19 -> 23070 | G62: 31000 | H62: 25400 | I62: 25400 | J62: 24700 | K62: 24000 | L62: 23200 | M62: =ROUND($F62*1.04,-2) -> 24000 | N62: =I62-$F62 -> 2330 | O62: =N62/I62 -> 0.091732283 | P62: =J62-$F62 -> 1630 | Q62: =P62/J62 -> 0.065991903 | R62: =K62-$F62 -> 930 | S62: =R62/K62 -> 0.03875 | T62: =L62-$F62 -> 130 | U62: =T62/L62 -> 0.0056034483 | V62: =M62-$F62 -> 930 | W62: =V62/M62 -> 0.03875
A63: Aura | B63: Aura Oversize T-Shirt | C63: Caramel | D63: XL | E63: tee_oversize | F63: ='Precios Tab Dreamfull-sheets'!$G$19 -> 23070 | G63: 31000 | H63: 25400 | I63: 25400 | J63: 24700 | K63: 24000 | L63: 23200 | M63: =ROUND($F63*1.04,-2) -> 24000 | N63: =I63-$F63 -> 2330 | O63: =N63/I63 -> 0.091732283 | P63: =J63-$F63 -> 1630 | Q63: =P63/J63 -> 0.065991903 | R63: =K63-$F63 -> 930 | S63: =R63/K63 -> 0.03875 | T63: =L63-$F63 -> 130 | U63: =T63/L63 -> 0.0056034483 | V63: =M63-$F63 -> 930 | W63: =V63/M63 -> 0.03875
A64: Aura | B64: Aura Oversize T-Shirt | C64: Negro | D64: 2XS | E64: tee_oversize | F64: ='Precios Tab Dreamfull-sheets'!$G$19 -> 23070 | G64: 31000 | H64: 25400 | I64: 25400 | J64: 24700 | K64: 24000 | L64: 23200 | M64: =ROUND($F64*1.04,-2) -> 24000 | N64: =I64-$F64 -> 2330 | O64: =N64/I64 -> 0.091732283 | P64: =J64-$F64 -> 1630 | Q64: =P64/J64 -> 0.065991903 | R64: =K64-$F64 -> 930 | S64: =R64/K64 -> 0.03875 | T64: =L64-$F64 -> 130 | U64: =T64/L64 -> 0.0056034483 | V64: =M64-$F64 -> 930 | W64: =V64/M64 -> 0.03875
A65: Aura | B65: Aura Oversize T-Shirt | C65: Negro | D65: XS | E65: tee_oversize | F65: ='Precios Tab Dreamfull-sheets'!$G$19 -> 23070 | G65: 31000 | H65: 25400 | I65: 25400 | J65: 24700 | K65: 24000 | L65: 23200 | M65: =ROUND($F65*1.04,-2) -> 24000 | N65: =I65-$F65 -> 2330 | O65: =N65/I65 -> 0.091732283 | P65: =J65-$F65 -> 1630 | Q65: =P65/J65 -> 0.065991903 | R65: =K65-$F65 -> 930 | S65: =R65/K65 -> 0.03875 | T65: =L65-$F65 -> 130 | U65: =T65/L65 -> 0.0056034483 | V65: =M65-$F65 -> 930 | W65: =V65/M65 -> 0.03875
A66: Aura | B66: Aura Oversize T-Shirt | C66: Negro | D66: S | E66: tee_oversize | F66: ='Precios Tab Dreamfull-sheets'!$G$19 -> 23070 | G66: 31000 | H66: 25400 | I66: 25400 | J66: 24700 | K66: 24000 | L66: 23200 | M66: =ROUND($F66*1.04,-2) -> 24000 | N66: =I66-$F66 -> 2330 | O66: =N66/I66 -> 0.091732283 | P66: =J66-$F66 -> 1630 | Q66: =P66/J66 -> 0.065991903 | R66: =K66-$F66 -> 930 | S66: =R66/K66 -> 0.03875 | T66: =L66-$F66 -> 130 | U66: =T66/L66 -> 0.0056034483 | V66: =M66-$F66 -> 930 | W66: =V66/M66 -> 0.03875
A67: Aura | B67: Aura Oversize T-Shirt | C67: Negro | D67: M | E67: tee_oversize | F67: ='Precios Tab Dreamfull-sheets'!$G$19 -> 23070 | G67: 31000 | H67: 25400 | I67: 25400 | J67: 24700 | K67: 24000 | L67: 23200 | M67: =ROUND($F67*1.04,-2) -> 24000 | N67: =I67-$F67 -> 2330 | O67: =N67/I67 -> 0.091732283 | P67: =J67-$F67 -> 1630 | Q67: =P67/J67 -> 0.065991903 | R67: =K67-$F67 -> 930 | S67: =R67/K67 -> 0.03875 | T67: =L67-$F67 -> 130 | U67: =T67/L67 -> 0.0056034483 | V67: =M67-$F67 -> 930 | W67: =V67/M67 -> 0.03875
A68: Aura | B68: Aura Oversize T-Shirt | C68: Negro | D68: L | E68: tee_oversize | F68: ='Precios Tab Dreamfull-sheets'!$G$19 -> 23070 | G68: 31000 | H68: 25400 | I68: 25400 | J68: 24700 | K68: 24000 | L68: 23200 | M68: =ROUND($F68*1.04,-2) -> 24000 | N68: =I68-$F68 -> 2330 | O68: =N68/I68 -> 0.091732283 | P68: =J68-$F68 -> 1630 | Q68: =P68/J68 -> 0.065991903 | R68: =K68-$F68 -> 930 | S68: =R68/K68 -> 0.03875 | T68: =L68-$F68 -> 130 | U68: =T68/L68 -> 0.0056034483 | V68: =M68-$F68 -> 930 | W68: =V68/M68 -> 0.03875
A69: Aura | B69: Aura Oversize T-Shirt | C69: Negro | D69: XL | E69: tee_oversize | F69: ='Precios Tab Dreamfull-sheets'!$G$19 -> 23070 | G69: 31000 | H69: 25400 | I69: 25400 | J69: 24700 | K69: 24000 | L69: 23200 | M69: =ROUND($F69*1.04,-2) -> 24000 | N69: =I69-$F69 -> 2330 | O69: =N69/I69 -> 0.091732283 | P69: =J69-$F69 -> 1630 | Q69: =P69/J69 -> 0.065991903 | R69: =K69-$F69 -> 930 | S69: =R69/K69 -> 0.03875 | T69: =L69-$F69 -> 130 | U69: =T69/L69 -> 0.0056034483 | V69: =M69-$F69 -> 930 | W69: =V69/M69 -> 0.03875
A70: Aura | B70: Aura Oversize T-Shirt | C70: Negro | D70: 2XL | E70: tee_oversize | F70: ='Precios Tab Dreamfull-sheets'!$G$19 -> 23070 | G70: 31000 | H70: 25400 | I70: 25400 | J70: 24700 | K70: 24000 | L70: 23200 | M70: =ROUND($F70*1.04,-2) -> 24000 | N70: =I70-$F70 -> 2330 | O70: =N70/I70 -> 0.091732283 | P70: =J70-$F70 -> 1630 | Q70: =P70/J70 -> 0.065991903 | R70: =K70-$F70 -> 930 | S70: =R70/K70 -> 0.03875 | T70: =L70-$F70 -> 130 | U70: =T70/L70 -> 0.0056034483 | V70: =M70-$F70 -> 930 | W70: =V70/M70 -> 0.03875
A71: Aura | B71: Aura Oversize T-Shirt | C71: Stone Wash | D71: S | E71: tee_oversize | F71: ='Precios Tab Dreamfull-sheets'!$G$20 -> 23470 | G71: 31000 | H71: 25400 | I71: 25400 | J71: 24700 | K71: 24000 | L71: =ROUND($F71*1.04,-2) -> 24400 | M71: =ROUND($F71*1.04,-2) -> 24400 | N71: =I71-$F71 -> 1930 | O71: =N71/I71 -> 0.075984252 | P71: =J71-$F71 -> 1230 | Q71: =P71/J71 -> 0.049797571 | R71: =K71-$F71 -> 530 | S71: =R71/K71 -> 0.022083333 | T71: =L71-$F71 -> 930 | U71: =T71/L71 -> 0.038114754 | V71: =M71-$F71 -> 930 | W71: =V71/M71 -> 0.038114754
A72: Aura | B72: Aura Oversize T-Shirt | C72: Stone Wash | D72: M | E72: tee_oversize | F72: ='Precios Tab Dreamfull-sheets'!$G$20 -> 23470 | G72: 31000 | H72: 25400 | I72: 25400 | J72: 24700 | K72: 24000 | L72: =ROUND($F72*1.04,-2) -> 24400 | M72: =ROUND($F72*1.04,-2) -> 24400 | N72: =I72-$F72 -> 1930 | O72: =N72/I72 -> 0.075984252 | P72: =J72-$F72 -> 1230 | Q72: =P72/J72 -> 0.049797571 | R72: =K72-$F72 -> 530 | S72: =R72/K72 -> 0.022083333 | T72: =L72-$F72 -> 930 | U72: =T72/L72 -> 0.038114754 | V72: =M72-$F72 -> 930 | W72: =V72/M72 -> 0.038114754
A73: Aura | B73: Aura Oversize T-Shirt | C73: Stone Wash | D73: L | E73: tee_oversize | F73: ='Precios Tab Dreamfull-sheets'!$G$20 -> 23470 | G73: 31000 | H73: 25400 | I73: 25400 | J73: 24700 | K73: 24000 | L73: =ROUND($F73*1.04,-2) -> 24400 | M73: =ROUND($F73*1.04,-2) -> 24400 | N73: =I73-$F73 -> 1930 | O73: =N73/I73 -> 0.075984252 | P73: =J73-$F73 -> 1230 | Q73: =P73/J73 -> 0.049797571 | R73: =K73-$F73 -> 530 | S73: =R73/K73 -> 0.022083333 | T73: =L73-$F73 -> 930 | U73: =T73/L73 -> 0.038114754 | V73: =M73-$F73 -> 930 | W73: =V73/M73 -> 0.038114754
A74: Aura | B74: Aura Oversize T-Shirt | C74: Stone Wash | D74: XL | E74: tee_oversize | F74: ='Precios Tab Dreamfull-sheets'!$G$20 -> 23470 | G74: 31000 | H74: 25400 | I74: 25400 | J74: 24700 | K74: 24000 | L74: =ROUND($F74*1.04,-2) -> 24400 | M74: =ROUND($F74*1.04,-2) -> 24400 | N74: =I74-$F74 -> 1930 | O74: =N74/I74 -> 0.075984252 | P74: =J74-$F74 -> 1230 | Q74: =P74/J74 -> 0.049797571 | R74: =K74-$F74 -> 530 | S74: =R74/K74 -> 0.022083333 | T74: =L74-$F74 -> 930 | U74: =T74/L74 -> 0.038114754 | V74: =M74-$F74 -> 930 | W74: =V74/M74 -> 0.038114754
A75: Aldea Classic Fit | B75: Aldea Classic Fit T-Shirt | C75: Blanco | D75: S | E75: tee_classic | F75: ='Precios Tab Dreamfull-sheets'!$G$14 -> 18600 | G75: 28600 | H75: 25700 | I75: 25700 | J75: 24700 | K75: 23700 | L75: 22700 | M75: 21700 | N75: =I75-$F75 -> 7100 | O75: =N75/I75 -> 0.27626459 | P75: =J75-$F75 -> 6100 | Q75: =P75/J75 -> 0.24696356 | R75: =K75-$F75 -> 5100 | S75: =R75/K75 -> 0.21518987 | T75: =L75-$F75 -> 4100 | U75: =T75/L75 -> 0.18061674 | V75: =M75-$F75 -> 3100 | W75: =V75/M75 -> 0.14285714
A76: Aldea Classic Fit | B76: Aldea Classic Fit T-Shirt | C76: Blanco | D76: M | E76: tee_classic | F76: ='Precios Tab Dreamfull-sheets'!$G$14 -> 18600 | G76: 28600 | H76: 25700 | I76: 25700 | J76: 24700 | K76: 23700 | L76: 22700 | M76: 21700 | N76: =I76-$F76 -> 7100 | O76: =N76/I76 -> 0.27626459 | P76: =J76-$F76 -> 6100 | Q76: =P76/J76 -> 0.24696356 | R76: =K76-$F76 -> 5100 | S76: =R76/K76 -> 0.21518987 | T76: =L76-$F76 -> 4100 | U76: =T76/L76 -> 0.18061674 | V76: =M76-$F76 -> 3100 | W76: =V76/M76 -> 0.14285714
A77: Aldea Classic Fit | B77: Aldea Classic Fit T-Shirt | C77: Blanco | D77: L | E77: tee_classic | F77: ='Precios Tab Dreamfull-sheets'!$G$14 -> 18600 | G77: 28600 | H77: 25700 | I77: 25700 | J77: 24700 | K77: 23700 | L77: 22700 | M77: 21700 | N77: =I77-$F77 -> 7100 | O77: =N77/I77 -> 0.27626459 | P77: =J77-$F77 -> 6100 | Q77: =P77/J77 -> 0.24696356 | R77: =K77-$F77 -> 5100 | S77: =R77/K77 -> 0.21518987 | T77: =L77-$F77 -> 4100 | U77: =T77/L77 -> 0.18061674 | V77: =M77-$F77 -> 3100 | W77: =V77/M77 -> 0.14285714
A78: Aldea Classic Fit | B78: Aldea Classic Fit T-Shirt | C78: Blanco | D78: XL | E78: tee_classic | F78: ='Precios Tab Dreamfull-sheets'!$G$14 -> 18600 | G78: 28600 | H78: 25700 | I78: 25700 | J78: 24700 | K78: 23700 | L78: 22700 | M78: 21700 | N78: =I78-$F78 -> 7100 | O78: =N78/I78 -> 0.27626459 | P78: =J78-$F78 -> 6100 | Q78: =P78/J78 -> 0.24696356 | R78: =K78-$F78 -> 5100 | S78: =R78/K78 -> 0.21518987 | T78: =L78-$F78 -> 4100 | U78: =T78/L78 -> 0.18061674 | V78: =M78-$F78 -> 3100 | W78: =V78/M78 -> 0.14285714
A79: Aldea Classic Fit | B79: Aldea Classic Fit T-Shirt | C79: Blanco | D79: 2XL | E79: tee_classic | F79: ='Precios Tab Dreamfull-sheets'!$G$14 -> 18600 | G79: 28600 | H79: 25700 | I79: 25700 | J79: 24700 | K79: 23700 | L79: 22700 | M79: 21700 | N79: =I79-$F79 -> 7100 | O79: =N79/I79 -> 0.27626459 | P79: =J79-$F79 -> 6100 | Q79: =P79/J79 -> 0.24696356 | R79: =K79-$F79 -> 5100 | S79: =R79/K79 -> 0.21518987 | T79: =L79-$F79 -> 4100 | U79: =T79/L79 -> 0.18061674 | V79: =M79-$F79 -> 3100 | W79: =V79/M79 -> 0.14285714
A80: Aldea Classic Fit | B80: Aldea Classic Fit T-Shirt | C80: Negro | D80: S | E80: tee_classic | F80: ='Precios Tab Dreamfull-sheets'!$G$15 -> 22670 | G80: 28600 | H80: 25700 | I80: 25700 | J80: 24700 | K80: 23700 | L80: 22700 | M80: =ROUND($F80*1.04,-2) -> 23600 | N80: =I80-$F80 -> 3030 | O80: =N80/I80 -> 0.11789883 | P80: =J80-$F80 -> 2030 | Q80: =P80/J80 -> 0.082186235 | R80: =K80-$F80 -> 1030 | S80: =R80/K80 -> 0.043459916 | T80: =L80-$F80 -> 30 | U80: =T80/L80 -> 0.0013215859 | V80: =M80-$F80 -> 930 | W80: =V80/M80 -> 0.03940678
A81: Aldea Classic Fit | B81: Aldea Classic Fit T-Shirt | C81: Negro | D81: M | E81: tee_classic | F81: ='Precios Tab Dreamfull-sheets'!$G$15 -> 22670 | G81: 28600 | H81: 25700 | I81: 25700 | J81: 24700 | K81: 23700 | L81: 22700 | M81: =ROUND($F81*1.04,-2) -> 23600 | N81: =I81-$F81 -> 3030 | O81: =N81/I81 -> 0.11789883 | P81: =J81-$F81 -> 2030 | Q81: =P81/J81 -> 0.082186235 | R81: =K81-$F81 -> 1030 | S81: =R81/K81 -> 0.043459916 | T81: =L81-$F81 -> 30 | U81: =T81/L81 -> 0.0013215859 | V81: =M81-$F81 -> 930 | W81: =V81/M81 -> 0.03940678
A82: Aldea Classic Fit | B82: Aldea Classic Fit T-Shirt | C82: Negro | D82: L | E82: tee_classic | F82: ='Precios Tab Dreamfull-sheets'!$G$15 -> 22670 | G82: 28600 | H82: 25700 | I82: 25700 | J82: 24700 | K82: 23700 | L82: 22700 | M82: =ROUND($F82*1.04,-2) -> 23600 | N82: =I82-$F82 -> 3030 | O82: =N82/I82 -> 0.11789883 | P82: =J82-$F82 -> 2030 | Q82: =P82/J82 -> 0.082186235 | R82: =K82-$F82 -> 1030 | S82: =R82/K82 -> 0.043459916 | T82: =L82-$F82 -> 30 | U82: =T82/L82 -> 0.0013215859 | V82: =M82-$F82 -> 930 | W82: =V82/M82 -> 0.03940678
A83: Aldea Classic Fit | B83: Aldea Classic Fit T-Shirt | C83: Negro | D83: XL | E83: tee_classic | F83: ='Precios Tab Dreamfull-sheets'!$G$15 -> 22670 | G83: 28600 | H83: 25700 | I83: 25700 | J83: 24700 | K83: 23700 | L83: 22700 | M83: =ROUND($F83*1.04,-2) -> 23600 | N83: =I83-$F83 -> 3030 | O83: =N83/I83 -> 0.11789883 | P83: =J83-$F83 -> 2030 | Q83: =P83/J83 -> 0.082186235 | R83: =K83-$F83 -> 1030 | S83: =R83/K83 -> 0.043459916 | T83: =L83-$F83 -> 30 | U83: =T83/L83 -> 0.0013215859 | V83: =M83-$F83 -> 930 | W83: =V83/M83 -> 0.03940678
A84: Aldea Classic Fit | B84: Aldea Classic Fit T-Shirt | C84: Negro | D84: 2XL | E84: tee_classic | F84: ='Precios Tab Dreamfull-sheets'!$G$15 -> 22670 | G84: 28600 | H84: 25700 | I84: 25700 | J84: 24700 | K84: 23700 | L84: 22700 | M84: =ROUND($F84*1.04,-2) -> 23600 | N84: =I84-$F84 -> 3030 | O84: =N84/I84 -> 0.11789883 | P84: =J84-$F84 -> 2030 | Q84: =P84/J84 -> 0.082186235 | R84: =K84-$F84 -> 1030 | S84: =R84/K84 -> 0.043459916 | T84: =L84-$F84 -> 30 | U84: =T84/L84 -> 0.0013215859 | V84: =M84-$F84 -> 930 | W84: =V84/M84 -> 0.03940678
A85: Buenos Aires | B85: Remera Clásica Mujer | C85: Blanca | D85: S | E85: tee_classic | F85: ='Precios Tab Dreamfull-sheets'!$G$16 -> 18600 | G85: 28600 | H85: 25700 | I85: 25700 | J85: 24700 | K85: 23700 | L85: 22700 | M85: 21700 | N85: =I85-$F85 -> 7100 | O85: =N85/I85 -> 0.27626459 | P85: =J85-$F85 -> 6100 | Q85: =P85/J85 -> 0.24696356 | R85: =K85-$F85 -> 5100 | S85: =R85/K85 -> 0.21518987 | T85: =L85-$F85 -> 4100 | U85: =T85/L85 -> 0.18061674 | V85: =M85-$F85 -> 3100 | W85: =V85/M85 -> 0.14285714
A86: Buenos Aires | B86: Remera Clásica Mujer | C86: Blanca | D86: M | E86: tee_classic | F86: ='Precios Tab Dreamfull-sheets'!$G$16 -> 18600 | G86: 28600 | H86: 25700 | I86: 25700 | J86: 24700 | K86: 23700 | L86: 22700 | M86: 21700 | N86: =I86-$F86 -> 7100 | O86: =N86/I86 -> 0.27626459 | P86: =J86-$F86 -> 6100 | Q86: =P86/J86 -> 0.24696356 | R86: =K86-$F86 -> 5100 | S86: =R86/K86 -> 0.21518987 | T86: =L86-$F86 -> 4100 | U86: =T86/L86 -> 0.18061674 | V86: =M86-$F86 -> 3100 | W86: =V86/M86 -> 0.14285714
A87: Buenos Aires | B87: Remera Clásica Mujer | C87: Blanca | D87: L | E87: tee_classic | F87: ='Precios Tab Dreamfull-sheets'!$G$16 -> 18600 | G87: 28600 | H87: 25700 | I87: 25700 | J87: 24700 | K87: 23700 | L87: 22700 | M87: 21700 | N87: =I87-$F87 -> 7100 | O87: =N87/I87 -> 0.27626459 | P87: =J87-$F87 -> 6100 | Q87: =P87/J87 -> 0.24696356 | R87: =K87-$F87 -> 5100 | S87: =R87/K87 -> 0.21518987 | T87: =L87-$F87 -> 4100 | U87: =T87/L87 -> 0.18061674 | V87: =M87-$F87 -> 3100 | W87: =V87/M87 -> 0.14285714
A88: Buenos Aires | B88: Remera Clásica Mujer | C88: Blanca | D88: XL | E88: tee_classic | F88: ='Precios Tab Dreamfull-sheets'!$G$16 -> 18600 | G88: 28600 | H88: 25700 | I88: 25700 | J88: 24700 | K88: 23700 | L88: 22700 | M88: 21700 | N88: =I88-$F88 -> 7100 | O88: =N88/I88 -> 0.27626459 | P88: =J88-$F88 -> 6100 | Q88: =P88/J88 -> 0.24696356 | R88: =K88-$F88 -> 5100 | S88: =R88/K88 -> 0.21518987 | T88: =L88-$F88 -> 4100 | U88: =T88/L88 -> 0.18061674 | V88: =M88-$F88 -> 3100 | W88: =V88/M88 -> 0.14285714
A89: Buenos Aires | B89: Remera Clásica Mujer | C89: Blanca | D89: 2XL | E89: tee_classic | F89: ='Precios Tab Dreamfull-sheets'!$G$16 -> 18600 | G89: 28600 | H89: 25700 | I89: 25700 | J89: 24700 | K89: 23700 | L89: 22700 | M89: 21700 | N89: =I89-$F89 -> 7100 | O89: =N89/I89 -> 0.27626459 | P89: =J89-$F89 -> 6100 | Q89: =P89/J89 -> 0.24696356 | R89: =K89-$F89 -> 5100 | S89: =R89/K89 -> 0.21518987 | T89: =L89-$F89 -> 4100 | U89: =T89/L89 -> 0.18061674 | V89: =M89-$F89 -> 3100 | W89: =V89/M89 -> 0.14285714
A90: Buenos Aires | B90: Remera Clásica Mujer | C90: Negra | D90: S | E90: tee_classic | F90: ='Precios Tab Dreamfull-sheets'!$G$17 -> 22670 | G90: 28600 | H90: 25700 | I90: 25700 | J90: 24700 | K90: 23700 | L90: 22700 | M90: =ROUND($F90*1.04,-2) -> 23600 | N90: =I90-$F90 -> 3030 | O90: =N90/I90 -> 0.11789883 | P90: =J90-$F90 -> 2030 | Q90: =P90/J90 -> 0.082186235 | R90: =K90-$F90 -> 1030 | S90: =R90/K90 -> 0.043459916 | T90: =L90-$F90 -> 30 | U90: =T90/L90 -> 0.0013215859 | V90: =M90-$F90 -> 930 | W90: =V90/M90 -> 0.03940678
A91: Buenos Aires | B91: Remera Clásica Mujer | C91: Negra | D91: M | E91: tee_classic | F91: ='Precios Tab Dreamfull-sheets'!$G$17 -> 22670 | G91: 28600 | H91: 25700 | I91: 25700 | J91: 24700 | K91: 23700 | L91: 22700 | M91: =ROUND($F91*1.04,-2) -> 23600 | N91: =I91-$F91 -> 3030 | O91: =N91/I91 -> 0.11789883 | P91: =J91-$F91 -> 2030 | Q91: =P91/J91 -> 0.082186235 | R91: =K91-$F91 -> 1030 | S91: =R91/K91 -> 0.043459916 | T91: =L91-$F91 -> 30 | U91: =T91/L91 -> 0.0013215859 | V91: =M91-$F91 -> 930 | W91: =V91/M91 -> 0.03940678
A92: Buenos Aires | B92: Remera Clásica Mujer | C92: Negra | D92: L | E92: tee_classic | F92: ='Precios Tab Dreamfull-sheets'!$G$17 -> 22670 | G92: 28600 | H92: 25700 | I92: 25700 | J92: 24700 | K92: 23700 | L92: 22700 | M92: =ROUND($F92*1.04,-2) -> 23600 | N92: =I92-$F92 -> 3030 | O92: =N92/I92 -> 0.11789883 | P92: =J92-$F92 -> 2030 | Q92: =P92/J92 -> 0.082186235 | R92: =K92-$F92 -> 1030 | S92: =R92/K92 -> 0.043459916 | T92: =L92-$F92 -> 30 | U92: =T92/L92 -> 0.0013215859 | V92: =M92-$F92 -> 930 | W92: =V92/M92 -> 0.03940678
A93: Buenos Aires | B93: Remera Clásica Mujer | C93: Negra | D93: XL | E93: tee_classic | F93: ='Precios Tab Dreamfull-sheets'!$G$17 -> 22670 | G93: 28600 | H93: 25700 | I93: 25700 | J93: 24700 | K93: 23700 | L93: 22700 | M93: =ROUND($F93*1.04,-2) -> 23600 | N93: =I93-$F93 -> 3030 | O93: =N93/I93 -> 0.11789883 | P93: =J93-$F93 -> 2030 | Q93: =P93/J93 -> 0.082186235 | R93: =K93-$F93 -> 1030 | S93: =R93/K93 -> 0.043459916 | T93: =L93-$F93 -> 30 | U93: =T93/L93 -> 0.0013215859 | V93: =M93-$F93 -> 930 | W93: =V93/M93 -> 0.03940678
A94: Buenos Aires | B94: Remera Clásica Mujer | C94: Negra | D94: 2XL | E94: tee_classic | F94: ='Precios Tab Dreamfull-sheets'!$G$17 -> 22670 | G94: 28600 | H94: 25700 | I94: 25700 | J94: 24700 | K94: 23700 | L94: 22700 | M94: =ROUND($F94*1.04,-2) -> 23600 | N94: =I94-$F94 -> 3030 | O94: =N94/I94 -> 0.11789883 | P94: =J94-$F94 -> 2030 | Q94: =P94/J94 -> 0.082186235 | R94: =K94-$F94 -> 1030 | S94: =R94/K94 -> 0.043459916 | T94: =L94-$F94 -> 30 | U94: =T94/L94 -> 0.0013215859 | V94: =M94-$F94 -> 930 | W94: =V94/M94 -> 0.03940678
A95: Bahamas | B95: Remera Crop Mujer | C95: Amarillo | D95: S | E95: crop | F95: ='Precios Tab Dreamfull-sheets'!$G$5 -> 18100 | G95: 23500 | H95: 19300 | I95: 19300 | J95: 18800 | K95: 18200 | L95: =ROUND($F95*1.04,-2) -> 18800 | M95: =ROUND($F95*1.04,-2) -> 18800 | N95: =I95-$F95 -> 1200 | O95: =N95/I95 -> 0.062176166 | P95: =J95-$F95 -> 700 | Q95: =P95/J95 -> 0.037234043 | R95: =K95-$F95 -> 100 | S95: =R95/K95 -> 0.0054945055 | T95: =L95-$F95 -> 700 | U95: =T95/L95 -> 0.037234043 | V95: =M95-$F95 -> 700 | W95: =V95/M95 -> 0.037234043
A96: Bahamas | B96: Remera Crop Mujer | C96: Amarillo | D96: M | E96: crop | F96: ='Precios Tab Dreamfull-sheets'!$G$5 -> 18100 | G96: 23500 | H96: 19300 | I96: 19300 | J96: 18800 | K96: 18200 | L96: =ROUND($F96*1.04,-2) -> 18800 | M96: =ROUND($F96*1.04,-2) -> 18800 | N96: =I96-$F96 -> 1200 | O96: =N96/I96 -> 0.062176166 | P96: =J96-$F96 -> 700 | Q96: =P96/J96 -> 0.037234043 | R96: =K96-$F96 -> 100 | S96: =R96/K96 -> 0.0054945055 | T96: =L96-$F96 -> 700 | U96: =T96/L96 -> 0.037234043 | V96: =M96-$F96 -> 700 | W96: =V96/M96 -> 0.037234043
A97: Bahamas | B97: Remera Crop Mujer | C97: Amarillo | D97: L | E97: crop | F97: ='Precios Tab Dreamfull-sheets'!$G$5 -> 18100 | G97: 23500 | H97: 19300 | I97: 19300 | J97: 18800 | K97: 18200 | L97: =ROUND($F97*1.04,-2) -> 18800 | M97: =ROUND($F97*1.04,-2) -> 18800 | N97: =I97-$F97 -> 1200 | O97: =N97/I97 -> 0.062176166 | P97: =J97-$F97 -> 700 | Q97: =P97/J97 -> 0.037234043 | R97: =K97-$F97 -> 100 | S97: =R97/K97 -> 0.0054945055 | T97: =L97-$F97 -> 700 | U97: =T97/L97 -> 0.037234043 | V97: =M97-$F97 -> 700 | W97: =V97/M97 -> 0.037234043
A98: Bahamas | B98: Remera Crop Mujer | C98: Amarillo | D98: XL | E98: crop | F98: ='Precios Tab Dreamfull-sheets'!$G$5 -> 18100 | G98: 23500 | H98: 19300 | I98: 19300 | J98: 18800 | K98: 18200 | L98: =ROUND($F98*1.04,-2) -> 18800 | M98: =ROUND($F98*1.04,-2) -> 18800 | N98: =I98-$F98 -> 1200 | O98: =N98/I98 -> 0.062176166 | P98: =J98-$F98 -> 700 | Q98: =P98/J98 -> 0.037234043 | R98: =K98-$F98 -> 100 | S98: =R98/K98 -> 0.0054945055 | T98: =L98-$F98 -> 700 | U98: =T98/L98 -> 0.037234043 | V98: =M98-$F98 -> 700 | W98: =V98/M98 -> 0.037234043
A99: Bahamas | B99: Remera Crop Mujer | C99: Amarillo | D99: 2XL | E99: crop | F99: ='Precios Tab Dreamfull-sheets'!$G$5 -> 18100 | G99: 23500 | H99: 19300 | I99: 19300 | J99: 18800 | K99: 18200 | L99: =ROUND($F99*1.04,-2) -> 18800 | M99: =ROUND($F99*1.04,-2) -> 18800 | N99: =I99-$F99 -> 1200 | O99: =N99/I99 -> 0.062176166 | P99: =J99-$F99 -> 700 | Q99: =P99/J99 -> 0.037234043 | R99: =K99-$F99 -> 100 | S99: =R99/K99 -> 0.0054945055 | T99: =L99-$F99 -> 700 | U99: =T99/L99 -> 0.037234043 | V99: =M99-$F99 -> 700 | W99: =V99/M99 -> 0.037234043
A100: Bahamas | B100: Remera Crop Mujer | C100: Chocolate | D100: S | E100: crop | F100: ='Precios Tab Dreamfull-sheets'!$G$5 -> 18100 | G100: 23500 | H100: 19300 | I100: 19300 | J100: 18800 | K100: 18200 | L100: =ROUND($F100*1.04,-2) -> 18800 | M100: =ROUND($F100*1.04,-2) -> 18800 | N100: =I100-$F100 -> 1200 | O100: =N100/I100 -> 0.062176166 | P100: =J100-$F100 -> 700 | Q100: =P100/J100 -> 0.037234043 | R100: =K100-$F100 -> 100 | S100: =R100/K100 -> 0.0054945055 | T100: =L100-$F100 -> 700 | U100: =T100/L100 -> 0.037234043 | V100: =M100-$F100 -> 700 | W100: =V100/M100 -> 0.037234043
A101: Bahamas | B101: Remera Crop Mujer | C101: Chocolate | D101: M | E101: crop | F101: ='Precios Tab Dreamfull-sheets'!$G$5 -> 18100 | G101: 23500 | H101: 19300 | I101: 19300 | J101: 18800 | K101: 18200 | L101: =ROUND($F101*1.04,-2) -> 18800 | M101: =ROUND($F101*1.04,-2) -> 18800 | N101: =I101-$F101 -> 1200 | O101: =N101/I101 -> 0.062176166 | P101: =J101-$F101 -> 700 | Q101: =P101/J101 -> 0.037234043 | R101: =K101-$F101 -> 100 | S101: =R101/K101 -> 0.0054945055 | T101: =L101-$F101 -> 700 | U101: =T101/L101 -> 0.037234043 | V101: =M101-$F101 -> 700 | W101: =V101/M101 -> 0.037234043
A102: Bahamas | B102: Remera Crop Mujer | C102: Chocolate | D102: L | E102: crop | F102: ='Precios Tab Dreamfull-sheets'!$G$5 -> 18100 | G102: 23500 | H102: 19300 | I102: 19300 | J102: 18800 | K102: 18200 | L102: =ROUND($F102*1.04,-2) -> 18800 | M102: =ROUND($F102*1.04,-2) -> 18800 | N102: =I102-$F102 -> 1200 | O102: =N102/I102 -> 0.062176166 | P102: =J102-$F102 -> 700 | Q102: =P102/J102 -> 0.037234043 | R102: =K102-$F102 -> 100 | S102: =R102/K102 -> 0.0054945055 | T102: =L102-$F102 -> 700 | U102: =T102/L102 -> 0.037234043 | V102: =M102-$F102 -> 700 | W102: =V102/M102 -> 0.037234043
...

Sheet Resumen_por_Producto
A1: Nombre_Comercial | B1: Producto | C1: Costo_Min | D1: Costo_Max | E1: B2C | F1: Muestra | G1: Partner (1u) | H1: Starter (5-9u) | I1: Pro (10-20u) | J1: Drop (30-99u) | K1: Bulk (100+u) | L1: Margen%_Partner_min | M1: Margen%_Bulk_max | N1: Tier_Starter_Cant | O1: Tier_Pro_Cant | P1: Tier_Drop_Cant | Q1: Tier_Bulk_Cant
B2: Buzo Cuello Redondo | C2: =MIN(Precios_Para_Comunicar!E2:E4) -> 24100 | D2: =MAX(Precios_Para_Comunicar!E2:E4) -> 28170 | E2: 43000 | F2: 32200 | G2: =MIN(Precios_Para_Comunicar!H2:H4) -> 32200 | H2: =MIN(Precios_Para_Comunicar!I2:I4) -> 31200 | I2: =MIN(Precios_Para_Comunicar!J2:J4) -> 30200 | J2: =MIN(Precios_Para_Comunicar!K2:K4) -> 29200 | K2: =MIN(Precios_Para_Comunicar!L2:L4) -> 28200 | L2: =MIN(Precios_Para_Comunicar!M2:M4) -> 0.12515528 | M2: =MAX(Precios_Para_Comunicar!Q2:Q4) -> 0.14539007 | N2: 5-9 u | O2: 10-20 u | P2: 30-99 u | Q2: 100+ u
B3: Buzo Hoodie Unisex | C3: =MIN(Precios_Para_Comunicar!E5:E10) -> 25100 | D3: =MAX(Precios_Para_Comunicar!E5:E10) -> 30170 | E3: 55000 | F3: 38700 | G3: =MIN(Precios_Para_Comunicar!H5:H10) -> 38700 | H3: =MIN(Precios_Para_Comunicar!I5:I10) -> 36600 | I3: =MIN(Precios_Para_Comunicar!J5:J10) -> 34500 | J3: =MIN(Precios_Para_Comunicar!K5:K10) -> 32400 | K3: =MIN(Precios_Para_Comunicar!L5:L10) -> 30300 | L3: =MIN(Precios_Para_Comunicar!M5:M10) -> 0.22041344 | M3: =MAX(Precios_Para_Comunicar!Q5:Q10) -> 0.17161716 | N3: 5-9 u | O3: 10-20 u | P3: 30-99 u | Q3: 100+ u
B4: Aura Oversize T-Shirt | C4: =MIN(Precios_Para_Comunicar!E11:E14) -> 19000 | D4: =MAX(Precios_Para_Comunicar!E11:E14) -> 23470 | E4: 31000 | F4: 25400 | G4: =MIN(Precios_Para_Comunicar!H11:H14) -> 26600 | H4: =MIN(Precios_Para_Comunicar!I11:I14) -> 25900 | I4: =MIN(Precios_Para_Comunicar!J11:J14) -> 25100 | J4: =MIN(Precios_Para_Comunicar!K11:K14) -> 24300 | K4: =MIN(Precios_Para_Comunicar!L11:L14) -> 23600 | L4: =MIN(Precios_Para_Comunicar!M11:M14) -> 0.11766917 | M4: =MAX(Precios_Para_Comunicar!Q11:Q14) -> 0.19491525 | N4: 5-9 u | O4: 10-20 u | P4: 30-99 u | Q4: 100+ u
B5: Aldea Classic Fit T-Shirt | C5: =MIN(Precios_Para_Comunicar!E15:E16) -> 18600 | D5: =MAX(Precios_Para_Comunicar!E15:E16) -> 22670 | E5: 28600 | F5: 25700 | G5: =MIN(Precios_Para_Comunicar!H15:H16) -> 25800 | H5: =MIN(Precios_Para_Comunicar!I15:I16) -> 25100 | I5: =MIN(Precios_Para_Comunicar!J15:J16) -> 24400 | J5: =MIN(Precios_Para_Comunicar!K15:K16) -> 23800 | K5: =MIN(Precios_Para_Comunicar!L15:L16) -> 23600 | L5: =MIN(Precios_Para_Comunicar!M15:M16) -> 0.12131783 | M5: =MAX(Precios_Para_Comunicar!Q15:Q16) -> 0.21186441 | N5: 5-9 u | O5: 10-20 u | P5: 30-99 u | Q5: 100+ u
B6: Remera Clásica Mujer | C6: =MIN(Precios_Para_Comunicar!E17:E18) -> 18600 | D6: =MAX(Precios_Para_Comunicar!E17:E18) -> 22670 | E6: 28600 | F6: 25700 | G6: =MIN(Precios_Para_Comunicar!H17:H18) -> 25800 | H6: =MIN(Precios_Para_Comunicar!I17:I18) -> 25100 | I6: =MIN(Precios_Para_Comunicar!J17:J18) -> 24400 | J6: =MIN(Precios_Para_Comunicar!K17:K18) -> 23800 | K6: =MIN(Precios_Para_Comunicar!L17:L18) -> 23600 | L6: =MIN(Precios_Para_Comunicar!M17:M18) -> 0.12131783 | M6: =MAX(Precios_Para_Comunicar!Q17:Q18) -> 0.21186441 | N6: 5-9 u | O6: 10-20 u | P6: 30-99 u | Q6: 100+ u
B7: Remera Crop Mujer | C7: =MIN(Precios_Para_Comunicar!E19:E22) -> 18100 | D7: =MAX(Precios_Para_Comunicar!E19:E22) -> 18100 | E7: 23500 | F7: 19300 | G7: =MIN(Precios_Para_Comunicar!H19:H22) -> 20800 | H7: =MIN(Precios_Para_Comunicar!I19:I22) -> 20300 | I7: =MIN(Precios_Para_Comunicar!J19:J22) -> 19800 | J7: =MIN(Precios_Para_Comunicar!K19:K22) -> 19300 | K7: =MIN(Precios_Para_Comunicar!L19:L22) -> 18900 | L7: =MIN(Precios_Para_Comunicar!M19:M22) -> 0.12980769 | M7: =MAX(Precios_Para_Comunicar!Q19:Q22) -> 0.042328042 | N7: 5-9 u | O7: 10-20 u | P7: 30-99 u | Q7: 100+ u
B8: Musculosa Bali | C8: =MIN(Precios_Para_Comunicar!E23:E25) -> 18100 | D8: =MAX(Precios_Para_Comunicar!E23:E25) -> 18100 | E8: 21800 | F8: 17400 | G8: =MIN(Precios_Para_Comunicar!H23:H25) -> 20800 | H8: =MIN(Precios_Para_Comunicar!I23:I25) -> 20700 | I8: =MIN(Precios_Para_Comunicar!J23:J25) -> 20500 | J8: =MIN(Precios_Para_Comunicar!K23:K25) -> 20300 | K8: =MIN(Precios_Para_Comunicar!L23:L25) -> 20100 | L8: =MIN(Precios_Para_Comunicar!M23:M25) -> 0.12980769 | M8: =MAX(Precios_Para_Comunicar!Q23:Q25) -> 0.099502488 | N8: 5-9 u | O8: 10-20 u | P8: 30-99 u | Q8: 100+ u

Sheet Plan_Precios_Futuro
A1: PLAN DE PRECIOS A FUTURO — Calculadora dinámica de subas (B2C + tiers partners)
A2: Editá los márgenes objetivo (celdas azules). Los precios sugeridos recalculan solos. Costos linkeados a Resumen_por_Producto (recalculan si cambia Dreamfull).
A4: INPUTS — Margen objetivo por tier (editable)
A5: Tier | B5: Margen objetivo % | C5: Criterio / racional
A6: B2C | B6: mantener actual | C6: Retail ya sano (~47%); subir solo para conservar el margen % actual
A7: Partner (1u) | B7: 0.3 | C7: Compra chica, sostiene margen alto
A8: Starter (5-9u) | B8: 0.26 | C8: Atractivo, deja colchón p/ads
A9: Pro (10-20u) | B9: 0.22 | C9: Volumen medio
A10: Drop (30-99u) | B10: 0.18 | C10: Cubre ads + parte de envío bonificado
A11: Bulk (100+u) | B11: 0.14 | C11: Piso para no quedar en 0-7% como hoy
A13: RECOMENDACIONES POR PRODUCTO | K13: PRECIOS SUGERIDOS POR TIER (para alcanzar el margen objetivo de los inputs) | T13: MARGEN ACTUAL — PEOR CASO (cliente pide el color de mayor costo). Precio único al cliente vs costo del color más caro.
A14: Producto | B14: Costo base | C14: B2C actual | D14: B2C margen% actual | E14: B2C sugerido | F14: Suba B2C % | H14: Costo anterior (ref) | I14: B2C margen% previo | K14: Producto | L14: Partner sug. | M14: Starter sug. | N14: Pro sug. | O14: Drop sug. | P14: Bulk sug. | R14: Observación | T14: Producto | U14: Partner | V14: Starter | W14: Pro | X14: Drop | Y14: Bulk
A15: =Resumen_por_Producto!B2 -> Buzo Cuello Redondo | B15: =Resumen_por_Producto!D2 -> 28170 | C15: =Resumen_por_Producto!E2 -> 43000 | D15: =(C15-B15)/C15 -> 0.34488372 | E15: =ROUND(B15/(1-I15),-2) -> 46300 | F15: =E15/C15-1 -> 0.076744186 | H15: 26170 | I15: =(C15-H15)/C15 -> 0.39139535 | K15: =A15 -> Buzo Cuello Redondo | L15: =ROUND($B15/(1-$B$7),-2) -> 40200 | M15: =ROUND($B15/(1-$B$8),-2) -> 38100 | N15: =ROUND($B15/(1-$B$9),-2) -> 36100 | O15: =ROUND($B15/(1-$B$10),-2) -> 34400 | P15: =ROUND($B15/(1-$B$11),-2) -> 32800 | R15: =IF(F15>0.25,"Suba B2C fuerte: evaluar escalonar",IF(F15>0.12,"Suba B2C moderada","Suba B2C leve, OK")) -> Suba B2C leve, OK | T15: =A15 -> Buzo Cuello Redondo | U15: =(Resumen_por_Producto!G2-Resumen_por_Producto!$D2)/Resumen_por_Producto!G2 -> 0.12515528 | V15: =(Resumen_por_Producto!H2-Resumen_por_Producto!$D2)/Resumen_por_Producto!H2 -> 0.097115385 | W15: =(Resumen_por_Producto!I2-Resumen_por_Producto!$D2)/Resumen_por_Producto!I2 -> 0.067218543 | X15: =(Resumen_por_Producto!J2-Resumen_por_Producto!$D2)/Resumen_por_Producto!J2 -> 0.035273973 | Y15: =(Resumen_por_Producto!K2-Resumen_por_Producto!$D2)/Resumen_por_Producto!K2 -> 0.0010638298
A16: =Resumen_por_Producto!B3 -> Buzo Hoodie Unisex | B16: =Resumen_por_Producto!D3 -> 30170 | C16: =Resumen_por_Producto!E3 -> 55000 | D16: =(C16-B16)/C16 -> 0.45145455 | E16: =ROUND(B16/(1-I16),-2) -> 58900 | F16: =E16/C16-1 -> 0.070909091 | H16: 28170 | I16: =(C16-H16)/C16 -> 0.48781818 | K16: =A16 -> Buzo Hoodie Unisex | L16: =ROUND($B16/(1-$B$7),-2) -> 43100 | M16: =ROUND($B16/(1-$B$8),-2) -> 40800 | N16: =ROUND($B16/(1-$B$9),-2) -> 38700 | O16: =ROUND($B16/(1-$B$10),-2) -> 36800 | P16: =ROUND($B16/(1-$B$11),-2) -> 35100 | R16: =IF(F16>0.25,"Suba B2C fuerte: evaluar escalonar",IF(F16>0.12,"Suba B2C moderada","Suba B2C leve, OK")) -> Suba B2C leve, OK | T16: =A16 -> Buzo Hoodie Unisex | U16: =(Resumen_por_Producto!G3-Resumen_por_Producto!$D3)/Resumen_por_Producto!G3 -> 0.22041344 | V16: =(Resumen_por_Producto!H3-Resumen_por_Producto!$D3)/Resumen_por_Producto!H3 -> 0.17568306 | W16: =(Resumen_por_Producto!I3-Resumen_por_Producto!$D3)/Resumen_por_Producto!I3 -> 0.12550725 | X16: =(Resumen_por_Producto!J3-Resumen_por_Producto!$D3)/Resumen_por_Producto!J3 -> 0.06882716 | Y16: =(Resumen_por_Producto!K3-Resumen_por_Producto!$D3)/Resumen_por_Producto!K3 -> 0.004290429
A17: =Resumen_por_Producto!B4 -> Aura Oversize T-Shirt | B17: =Resumen_por_Producto!D4 -> 23470 | C17: =Resumen_por_Producto!E4 -> 31000 | D17: =(C17-B17)/C17 -> 0.24290323 | E17: =ROUND(B17/(1-I17),-2) -> 35500 | F17: =E17/C17-1 -> 0.14516129 | H17: 20496 | I17: =(C17-H17)/C17 -> 0.33883871 | K17: =A17 -> Aura Oversize T-Shirt | L17: =ROUND($B17/(1-$B$7),-2) -> 33500 | M17: =ROUND($B17/(1-$B$8),-2) -> 31700 | N17: =ROUND($B17/(1-$B$9),-2) -> 30100 | O17: =ROUND($B17/(1-$B$10),-2) -> 28600 | P17: =ROUND($B17/(1-$B$11),-2) -> 27300 | R17: =IF(F17>0.25,"Suba B2C fuerte: evaluar escalonar",IF(F17>0.12,"Suba B2C moderada","Suba B2C leve, OK")) -> Suba B2C moderada | T17: =A17 -> Aura Oversize T-Shirt | U17: =(Resumen_por_Producto!G4-Resumen_por_Producto!$D4)/Resumen_por_Producto!G4 -> 0.11766917 | V17: =(Resumen_por_Producto!H4-Resumen_por_Producto!$D4)/Resumen_por_Producto!H4 -> 0.093822394 | W17: =(Resumen_por_Producto!I4-Resumen_por_Producto!$D4)/Resumen_por_Producto!I4 -> 0.064940239 | X17: =(Resumen_por_Producto!J4-Resumen_por_Producto!$D4)/Resumen_por_Producto!J4 -> 0.034156379 | Y17: =(Resumen_por_Producto!K4-Resumen_por_Producto!$D4)/Resumen_por_Producto!K4 -> 0.0055084746
A18: =Resumen_por_Producto!B5 -> Aldea Classic Fit T-Shirt | B18: =Resumen_por_Producto!D5 -> 22670 | C18: =Resumen_por_Producto!E5 -> 28600 | D18: =(C18-B18)/C18 -> 0.20734266 | E18: =ROUND(B18/(1-I18),-2) -> 32900 | F18: =E18/C18-1 -> 0.15034965 | H18: 19696 | I18: =(C18-H18)/C18 -> 0.31132867 | K18: =A18 -> Aldea Classic Fit T-Shirt | L18: =ROUND($B18/(1-$B$7),-2) -> 32400 | M18: =ROUND($B18/(1-$B$8),-2) -> 30600 | N18: =ROUND($B18/(1-$B$9),-2) -> 29100 | O18: =ROUND($B18/(1-$B$10),-2) -> 27600 | P18: =ROUND($B18/(1-$B$11),-2) -> 26400 | R18: =IF(F18>0.25,"Suba B2C fuerte: evaluar escalonar",IF(F18>0.12,"Suba B2C moderada","Suba B2C leve, OK")) -> Suba B2C moderada | T18: =A18 -> Aldea Classic Fit T-Shirt | U18: =(Resumen_por_Producto!G5-Resumen_por_Producto!$D5)/Resumen_por_Producto!G5 -> 0.12131783 | V18: =(Resumen_por_Producto!H5-Resumen_por_Producto!$D5)/Resumen_por_Producto!H5 -> 0.096812749 | W18: =(Resumen_por_Producto!I5-Resumen_por_Producto!$D5)/Resumen_por_Producto!I5 -> 0.070901639 | X18: =(Resumen_por_Producto!J5-Resumen_por_Producto!$D5)/Resumen_por_Producto!J5 -> 0.047478992 | Y18: =(Resumen_por_Producto!K5-Resumen_por_Producto!$D5)/Resumen_por_Producto!K5 -> 0.03940678
A19: =Resumen_por_Producto!B6 -> Remera Clásica Mujer | B19: =Resumen_por_Producto!D6 -> 22670 | C19: =Resumen_por_Producto!E6 -> 28600 | D19: =(C19-B19)/C19 -> 0.20734266 | E19: =ROUND(B19/(1-I19),-2) -> 32900 | F19: =E19/C19-1 -> 0.15034965 | H19: 19696 | I19: =(C19-H19)/C19 -> 0.31132867 | K19: =A19 -> Remera Clásica Mujer | L19: =ROUND($B19/(1-$B$7),-2) -> 32400 | M19: =ROUND($B19/(1-$B$8),-2) -> 30600 | N19: =ROUND($B19/(1-$B$9),-2) -> 29100 | O19: =ROUND($B19/(1-$B$10),-2) -> 27600 | P19: =ROUND($B19/(1-$B$11),-2) -> 26400 | R19: =IF(F19>0.25,"Suba B2C fuerte: evaluar escalonar",IF(F19>0.12,"Suba B2C moderada","Suba B2C leve, OK")) -> Suba B2C moderada | T19: =A19 -> Remera Clásica Mujer | U19: =(Resumen_por_Producto!G6-Resumen_por_Producto!$D6)/Resumen_por_Producto!G6 -> 0.12131783 | V19: =(Resumen_por_Producto!H6-Resumen_por_Producto!$D6)/Resumen_por_Producto!H6 -> 0.096812749 | W19: =(Resumen_por_Producto!I6-Resumen_por_Producto!$D6)/Resumen_por_Producto!I6 -> 0.070901639 | X19: =(Resumen_por_Producto!J6-Resumen_por_Producto!$D6)/Resumen_por_Producto!J6 -> 0.047478992 | Y19: =(Resumen_por_Producto!K6-Resumen_por_Producto!$D6)/Resumen_por_Producto!K6 -> 0.03940678
A20: =Resumen_por_Producto!B7 -> Remera Crop Mujer | B20: =Resumen_por_Producto!D7 -> 18100 | C20: =Resumen_por_Producto!E7 -> 23500 | D20: =(C20-B20)/C20 -> 0.22978723 | E20: =ROUND(B20/(1-I20),-2) -> 28100 | F20: =E20/C20-1 -> 0.19574468 | H20: 15156 | I20: =(C20-H20)/C20 -> 0.35506383 | K20: =A20 -> Remera Crop Mujer | L20: =ROUND($B20/(1-$B$7),-2) -> 25900 | M20: =ROUND($B20/(1-$B$8),-2) -> 24500 | N20: =ROUND($B20/(1-$B$9),-2) -> 23200 | O20: =ROUND($B20/(1-$B$10),-2) -> 22100 | P20: =ROUND($B20/(1-$B$11),-2) -> 21000 | R20: =IF(F20>0.25,"Suba B2C fuerte: evaluar escalonar",IF(F20>0.12,"Suba B2C moderada","Suba B2C leve, OK")) -> Suba B2C moderada | T20: =A20 -> Remera Crop Mujer | U20: =(Resumen_por_Producto!G7-Resumen_por_Producto!$D7)/Resumen_por_Producto!G7 -> 0.12980769 | V20: =(Resumen_por_Producto!H7-Resumen_por_Producto!$D7)/Resumen_por_Producto!H7 -> 0.10837438 | W20: =(Resumen_por_Producto!I7-Resumen_por_Producto!$D7)/Resumen_por_Producto!I7 -> 0.085858586 | X20: =(Resumen_por_Producto!J7-Resumen_por_Producto!$D7)/Resumen_por_Producto!J7 -> 0.062176166 | Y20: =(Resumen_por_Producto!K7-Resumen_por_Producto!$D7)/Resumen_por_Producto!K7 -> 0.042328042
A21: =Resumen_por_Producto!B8 -> Musculosa Bali | B21: =Resumen_por_Producto!D8 -> 18100 | C21: =Resumen_por_Producto!E8 -> 21800 | D21: =(C21-B21)/C21 -> 0.16972477 | E21: =ROUND(B21/(1-I21),-2) -> 30100 | F21: =E21/C21-1 -> 0.38073394 | H21: 13096 | I21: =(C21-H21)/C21 -> 0.39926606 | K21: =A21 -> Musculosa Bali | L21: =ROUND($B21/(1-$B$7),-2) -> 25900 | M21: =ROUND($B21/(1-$B$8),-2) -> 24500 | N21: =ROUND($B21/(1-$B$9),-2) -> 23200 | O21: =ROUND($B21/(1-$B$10),-2) -> 22100 | P21: =ROUND($B21/(1-$B$11),-2) -> 21000 | R21: =IF(F21>0.25,"Suba B2C fuerte: evaluar escalonar",IF(F21>0.12,"Suba B2C moderada","Suba B2C leve, OK")) -> Suba B2C fuerte: evaluar escalonar | T21: =A21 -> Musculosa Bali | U21: =(Resumen_por_Producto!G8-Resumen_por_Producto!$D8)/Resumen_por_Producto!G8 -> 0.12980769 | V21: =(Resumen_por_Producto!H8-Resumen_por_Producto!$D8)/Resumen_por_Producto!H8 -> 0.12560386 | W21: =(Resumen_por_Producto!I8-Resumen_por_Producto!$D8)/Resumen_por_Producto!I8 -> 0.11707317 | X21: =(Resumen_por_Producto!J8-Resumen_por_Producto!$D8)/Resumen_por_Producto!J8 -> 0.10837438 | Y21: =(Resumen_por_Producto!K8-Resumen_por_Producto!$D8)/Resumen_por_Producto!K8 -> 0.099502488
T23: MARGEN ACTUAL — MEJOR CASO (cliente pide el color de menor costo).
A24: CÓMO USAR ESTA TAB | T24: Producto | U24: Partner | V24: Starter | W24: Pro | X24: Drop | Y24: Bulk
A25: 1) Cuando Dreamful cambie costos, actualizá la tab 'Precios Tab Dreamfull-sheets'. Costo base (col B) y márgenes recalculan solos acá. | T25: =A15 -> Buzo Cuello Redondo | U25: =(Resumen_por_Producto!G2-Resumen_por_Producto!$C2)/Resumen_por_Producto!G2 -> 0.2515528 | V25: =(Resumen_por_Producto!H2-Resumen_por_Producto!$C2)/Resumen_por_Producto!H2 -> 0.2275641 | W25: =(Resumen_por_Producto!I2-Resumen_por_Producto!$C2)/Resumen_por_Producto!I2 -> 0.20198675 | X25: =(Resumen_por_Producto!J2-Resumen_por_Producto!$C2)/Resumen_por_Producto!J2 -> 0.17465753 | Y25: =(Resumen_por_Producto!K2-Resumen_por_Producto!$C2)/Resumen_por_Producto!K2 -> 0.14539007
A26: 2) Ajustá los márgenes objetivo (celdas azules B7:B11) según qué tan agresivo querés ser en precio. Más bajo = más atractivo, menos margen para ads/envíos/IA. | T26: =A16 -> Buzo Hoodie Unisex | U26: =(Resumen_por_Producto!G3-Resumen_por_Producto!$C3)/Resumen_por_Producto!G3 -> 0.35142119 | V26: =(Resumen_por_Producto!H3-Resumen_por_Producto!$C3)/Resumen_por_Producto!H3 -> 0.31420765 | W26: =(Resumen_por_Producto!I3-Resumen_por_Producto!$C3)/Resumen_por_Producto!I3 -> 0.27246377 | X26: =(Resumen_por_Producto!J3-Resumen_por_Producto!$C3)/Resumen_por_Producto!J3 -> 0.22530864 | Y26: =(Resumen_por_Producto!K3-Resumen_por_Producto!$C3)/Resumen_por_Producto!K3 -> 0.17161716
A27: 3) Columna E = B2C sugerido para conservar el margen % que tenías antes del aumento (usa 'Costo anterior' col H como referencia; actualizá H si cambia la base). | T27: =A17 -> Aura Oversize T-Shirt | U27: =(Resumen_por_Producto!G4-Resumen_por_Producto!$C4)/Resumen_por_Producto!G4 -> 0.28571429 | V27: =(Resumen_por_Producto!H4-Resumen_por_Producto!$C4)/Resumen_por_Producto!H4 -> 0.26640927 | W27: =(Resumen_por_Producto!I4-Resumen_por_Producto!$C4)/Resumen_por_Producto!I4 -> 0.24302789 | X27: =(Resumen_por_Producto!J4-Resumen_por_Producto!$C4)/Resumen_por_Producto!J4 -> 0.218107 | Y27: =(Resumen_por_Producto!K4-Resumen_por_Producto!$C4)/Resumen_por_Producto!K4 -> 0.19491525
A28: 4) Columnas L:P = precio sugerido por tier para alcanzar el margen objetivo. Son precios piso recomendados; podés redondear hacia arriba para retail. | T28: =A18 -> Aldea Classic Fit T-Shirt | U28: =(Resumen_por_Producto!G5-Resumen_por_Producto!$C5)/Resumen_por_Producto!G5 -> 0.27906977 | V28: =(Resumen_por_Producto!H5-Resumen_por_Producto!$C5)/Resumen_por_Producto!H5 -> 0.25896414 | W28: =(Resumen_por_Producto!I5-Resumen_por_Producto!$C5)/Resumen_por_Producto!I5 -> 0.23770492 | X28: =(Resumen_por_Producto!J5-Resumen_por_Producto!$C5)/Resumen_por_Producto!J5 -> 0.21848739 | Y28: =(Resumen_por_Producto!K5-Resumen_por_Producto!$C5)/Resumen_por_Producto!K5 -> 0.21186441
A29: 5) Recordatorio: el margen debe cubrir ads, envíos bonificados y suscripciones de IA. Por eso el piso de Bulk es 14% y no menos. | T29: =A19 -> Remera Clásica Mujer | U29: =(Resumen_por_Producto!G6-Resumen_por_Producto!$C6)/Resumen_por_Producto!G6 -> 0.27906977 | V29: =(Resumen_por_Producto!H6-Resumen_por_Producto!$C6)/Resumen_por_Producto!H6 -> 0.25896414 | W29: =(Resumen_por_Producto!I6-Resumen_por_Producto!$C6)/Resumen_por_Producto!I6 -> 0.23770492 | X29: =(Resumen_por_Producto!J6-Resumen_por_Producto!$C6)/Resumen_por_Producto!J6 -> 0.21848739 | Y29: =(Resumen_por_Producto!K6-Resumen_por_Producto!$C6)/Resumen_por_Producto!K6 -> 0.21186441
T30: =A20 -> Remera Crop Mujer | U30: =(Resumen_por_Producto!G7-Resumen_por_Producto!$C7)/Resumen_por_Producto!G7 -> 0.12980769 | V30: =(Resumen_por_Producto!H7-Resumen_por_Producto!$C7)/Resumen_por_Producto!H7 -> 0.10837438 | W30: =(Resumen_por_Producto!I7-Resumen_por_Producto!$C7)/Resumen_por_Producto!I7 -> 0.085858586 | X30: =(Resumen_por_Producto!J7-Resumen_por_Producto!$C7)/Resumen_por_Producto!J7 -> 0.062176166 | Y30: =(Resumen_por_Producto!K7-Resumen_por_Producto!$C7)/Resumen_por_Producto!K7 -> 0.042328042
A31: EL PROBLEMA DE FONDO: costo por color, precio único | T31: =A21 -> Musculosa Bali | U31: =(Resumen_por_Producto!G8-Resumen_por_Producto!$C8)/Resumen_por_Producto!G8 -> 0.12980769 | V31: =(Resumen_por_Producto!H8-Resumen_por_Producto!$C8)/Resumen_por_Producto!H8 -> 0.12560386 | W31: =(Resumen_por_Producto!I8-Resumen_por_Producto!$C8)/Resumen_por_Producto!I8 -> 0.11707317 | X31: =(Resumen_por_Producto!J8-Resumen_por_Producto!$C8)/Resumen_por_Producto!J8 -> 0.10837438 | Y31: =(Resumen_por_Producto!K8-Resumen_por_Producto!$C8)/Resumen_por_Producto!K8 -> 0.099502488
A32: Dreamful te cobra distinto por color, pero vos cobrás un precio único por producto. Si el cliente arma el pedido en el color MÁS CARO (Negro/Stone Wash), ese es el margen que te queda — ver tabla PEOR CASO (rojo = perdés plata en ese color).
A33: Por eso los precios sugeridos (cols L:P) se calculan sobre el COSTO MÁXIMO (peor color): así, vendas el color que vendas, nunca bajás del margen objetivo.
A34: Alternativas si no querés subir el precio único tanto: (a) cobrar un recargo por colores premium (Negro/Stone Wash), (b) limitar los colores caros en pedidos grandes (Drop/Bulk), o (c) negociar con Dreamful para emparejar el costo entre colores.
A35: Los casos más críticos hoy (peor caso negativo): Oversize y Remeras Clásicas/Mujer en Negro y Stone Wash, tiers Drop y Bulk.
A38: AJUSTE DE PRECIOS PARTNER PARA GARANTIZAR 8% DE AHORRO AL PASAR A GROWTH
A39: Growth = precio UNICO por producto = costo del color mas caro + delta de tier (Partner+1000). Regla: el Partner normal debe ser >= Growth_Partner / 0.92 para que pasar a Growth ahorre min. 8%. Solo se ajustan productos que hoy ahorran < 8%.
A41: Producto | B41: Costo max | C41: Growth Partner (nuevo, unico) | D41: Partner normal ACTUAL | E41: Ahorro actual % | F41: Cumple 8%? | G41: Partner normal NUEVO | H41: Ahorro nuevo % | I41: Suba Partner %
A42: =A15 -> Buzo Cuello Redondo | B42: =Resumen_por_Producto!D2 -> 28170 | C42: =B42+1000 -> 29170 | D42: =Resumen_por_Producto!G2 -> 32200 | E42: =1-C42/D42 -> 0.094099379 | F42: =IF(E42>=0.08,"Si","No") -> Si | G42: =MAX(D42,CEILING(C42/0.92,100)) -> 32200 | H42: =1-C42/G42 -> 0.094099379 | I42: =G42/D42-1 -> 0
A43: =A16 -> Buzo Hoodie Unisex | B43: =Resumen_por_Producto!D3 -> 30170 | C43: =B43+1000 -> 31170 | D43: =Resumen_por_Producto!G3 -> 38700 | E43: =1-C43/D43 -> 0.19457364 | F43: =IF(E43>=0.08,"Si","No") -> Si | G43: =MAX(D43,CEILING(C43/0.92,100)) -> 38700 | H43: =1-C43/G43 -> 0.19457364 | I43: =G43/D43-1 -> 0
A44: =A17 -> Aura Oversize T-Shirt | B44: =Resumen_por_Producto!D4 -> 23470 | C44: =B44+1000 -> 24470 | D44: =Resumen_por_Producto!G4 -> 26600 | E44: =1-C44/D44 -> 0.080075188 | F44: =IF(E44>=0.08,"Si","No") -> Si | G44: =MAX(D44,CEILING(C44/0.92,100)) -> 26600 | H44: =1-C44/G44 -> 0.080075188 | I44: =G44/D44-1 -> 0
A45: =A18 -> Aldea Classic Fit T-Shirt | B45: =Resumen_por_Producto!D5 -> 22670 | C45: =B45+1000 -> 23670 | D45: =Resumen_por_Producto!G5 -> 25800 | E45: =1-C45/D45 -> 0.08255814 | F45: =IF(E45>=0.08,"Si","No") -> Si | G45: =MAX(D45,CEILING(C45/0.92,100)) -> 25800 | H45: =1-C45/G45 -> 0.08255814 | I45: =G45/D45-1 -> 0
A46: =A19 -> Remera Clásica Mujer | B46: =Resumen_por_Producto!D6 -> 22670 | C46: =B46+1000 -> 23670 | D46: =Resumen_por_Producto!G6 -> 25800 | E46: =1-C46/D46 -> 0.08255814 | F46: =IF(E46>=0.08,"Si","No") -> Si | G46: =MAX(D46,CEILING(C46/0.92,100)) -> 25800 | H46: =1-C46/G46 -> 0.08255814 | I46: =G46/D46-1 -> 0
A47: =A20 -> Remera Crop Mujer | B47: =Resumen_por_Producto!D7 -> 18100 | C47: =B47+1000 -> 19100 | D47: =Resumen_por_Producto!G7 -> 20800 | E47: =1-C47/D47 -> 0.081730769 | F47: =IF(E47>=0.08,"Si","No") -> Si | G47: =MAX(D47,CEILING(C47/0.92,100)) -> 20800 | H47: =1-C47/G47 -> 0.081730769 | I47: =G47/D47-1 -> 0
A48: =A21 -> Musculosa Bali | B48: =Resumen_por_Producto!D8 -> 18100 | C48: =B48+1000 -> 19100 | D48: =Resumen_por_Producto!G8 -> 20800 | E48: =1-C48/D48 -> 0.081730769 | F48: =IF(E48>=0.08,"Si","No") -> Si | G48: =MAX(D48,CEILING(C48/0.92,100)) -> 20800 | H48: =1-C48/G48 -> 0.081730769 | I48: =G48/D48-1 -> 0
A50: PRECIOS PARTNER FINALES — todos los tiers ajustados en proporción a la suba del Partner
A51: Cada tier se multiplica por (1 + suba% del Partner) y se redondea a centena. Growth = precio unico por producto (costo color mas caro + delta).
A52: Producto | B52: Suba % | C52: Partner (1u) | D52: Starter (5-9u) | E52: Pro (10-20u) | F52: Drop (30-99u) | G52: Bulk (100+u) | H52: Growth (unico)
A53: =A42 -> Buzo Cuello Redondo | B53: =I42 -> 0 | C53: =G42 -> 32200 | D53: =ROUND(Resumen_por_Producto!H2*(1+$B53),-2) -> 31200 | E53: =ROUND(Resumen_por_Producto!I2*(1+$B53),-2) -> 30200 | F53: =ROUND(Resumen_por_Producto!J2*(1+$B53),-2) -> 29200 | G53: =ROUND(Resumen_por_Producto!K2*(1+$B53),-2) -> 28200 | H53: =C42 -> 29170
A54: =A43 -> Buzo Hoodie Unisex | B54: =I43 -> 0 | C54: =G43 -> 38700 | D54: =ROUND(Resumen_por_Producto!H3*(1+$B54),-2) -> 36600 | E54: =ROUND(Resumen_por_Producto!I3*(1+$B54),-2) -> 34500 | F54: =ROUND(Resumen_por_Producto!J3*(1+$B54),-2) -> 32400 | G54: =ROUND(Resumen_por_Producto!K3*(1+$B54),-2) -> 30300 | H54: =C43 -> 31170
A55: =A44 -> Aura Oversize T-Shirt | B55: =I44 -> 0 | C55: =G44 -> 26600 | D55: =ROUND(Resumen_por_Producto!H4*(1+$B55),-2) -> 25900 | E55: =ROUND(Resumen_por_Producto!I4*(1+$B55),-2) -> 25100 | F55: =ROUND(Resumen_por_Producto!J4*(1+$B55),-2) -> 24300 | G55: =ROUND(Resumen_por_Producto!K4*(1+$B55),-2) -> 23600 | H55: =C44 -> 24470
A56: =A45 -> Aldea Classic Fit T-Shirt | B56: =I45 -> 0 | C56: =G45 -> 25800 | D56: 25100 | E56: 24400 | F56: 23800 | G56: 23600 | H56: =C45 -> 23670
A57: =A46 -> Remera Clásica Mujer | B57: =I46 -> 0 | C57: =G46 -> 25800 | D57: 25100 | E57: 24400 | F57: 23800 | G57: 23600 | H57: =C46 -> 23670
A58: =A47 -> Remera Crop Mujer | B58: =I47 -> 0 | C58: =G47 -> 20800 | D58: =C58-500 -> 20300 | E58: =C58-1000 -> 19800 | F58: =C58-1500 -> 19300 | G58: =C58-1900 -> 18900 | H58: =C47 -> 19100
A59: =A48 -> Musculosa Bali | B59: =I48 -> 0 | C59: =G48 -> 20800 | D59: =ROUND(Resumen_por_Producto!H8*(1+$B59),-2) -> 20700 | E59: =ROUND(Resumen_por_Producto!I8*(1+$B59),-2) -> 20500 | F59: =ROUND(Resumen_por_Producto!J8*(1+$B59),-2) -> 20300 | G59: =ROUND(Resumen_por_Producto!K8*(1+$B59),-2) -> 20100 | H59: =C48 -> 19100

Sheet Precios Tab Dreamfull-sheets
A1: SKU - Dreamful | B1: Producto - novamente | C1: Color | D1: CategoriaKey | E1: Cost_1_Print | F1: Chica | G1: Cost_2_Print | H1: Producto - dreamful
A2: BB | B2: Buzo Cuello Redondo | C2: Blanco | D2: crewneck | E2: 20600 | F2: 23600 | G2: 24100 | H2: Buzo cuello redondo blanco Friza
A3: BN | B3: Buzo Cuello Redondo | C3: Negro | D3: crewneck | E3: 23170 | F3: 26170 | G3: 28170 | H3: Buzo cuello redondo negro Friza
A4: BSW | B4: Buzo Cuello Redondo | C4: Stone Wash | D4: crewneck | E4: 23170 | F4: 26170 | G4: 28170 | H4: Buzo cuello redondo acid wash Friza
A5: RCC | B5: Remera Crop Mujer | C5: Amarillo | D5: crop | E5: 14600 | F5: 17600 | G5: 18100 | H5: crop
A6: RCV | B6: Remera Crop Mujer | C6: Chocolate | D6: crop | E6: 14600 | F6: 17600 | G6: 18100 | H6: crop
A7: RCG | B7: Remera Crop Mujer | C7: Gris Melange | D7: crop | E7: 14600 | F7: 17600 | G7: 18100 | H7: crop
A8: RCN | B8: Remera Crop Mujer | C8: Negra | D8: crop | E8: 14600 | F8: 17600 | G8: 18100 | H8: crop
A9: HB | B9: Buzo Hoodie Unisex | C9: Blanco | D9: hoodie | E9: 21600 | F9: 24600 | G9: 25100 | H9: Canguro liso blanco Friza
A10: HN | B10: Buzo Hoodie Unisex | C10: Negro | D10: hoodie | E10: 24170 | F10: 27170 | G10: 29170 | H10: Canguro liso negro Friza
A11: HSW | B11: Buzo Hoodie Unisex | C11: Stone Wash | D11: hoodie | E11: 25170 | F11: 28170 | G11: 30170 | H11: Canguro stone wash Friza
A12: MMB | B12: Musculosa Bali | C12: Blanca | D12: tank | E12: 14600 | F12: 17600 | G12: 18100 | H12: Musculosas morley
A13: MMG | B13: Musculosa Bali | C13: Gris | D13: tank | E13: 14600 | F13: 17600 | G13: 18100 | H13: Musculosas morley
... A20: ROSW | B20: Aura Oversize T-Shirt | C20: Stone Wash | D20: tee_oversize | E20: 18470 | F20: 21470 | G20: 23470 | H20: Remera Over stone wash

Sheet Analisis_Descuentos
A1: Análisis Escalera de Descuentos por Volumen
A2: Base: B2C Precio Nuevo | Piso de margen aceptable: 15% | Costo = Cost_2_Print (con estampa completa)
A4: 1) TABLA POR PRODUCTO — Precio actual, costo, márgenes a distintos descuentos
A6: Producto | B6: Categoría | C6: Costo | D6: Precio Actual | E6: Margen $ s/desc | F6: Margen % s/desc | G6: P c/10% | H6: M$ 10% | I6: M% 10% | J6: P c/15% | K6: M$ 15% | L6: M% 15% | M6: P c/20% | N6: M$ 20% | O6: M% 20% | P6: P c/25% | Q6: M$ 25% | R6: M% 25% | S6: P c/30% | T6: M$ 30% | U6: M% 30% | V6: Max % off con 15% margen | W6: Observación
A7: Buzo Hoodie Unisex | B7: hoodie | C7: 28170 | D7: 55000 | E7: =D7-C7 -> 26830 | F7: =E7/D7 -> 0.48781818 | G7: =D7*0.9 -> 49500 | H7: =G7-C7 -> 21330 | I7: =H7/G7 -> 0.43090909 | J7: =D7*0.85 -> 46750 | K7: =J7-C7 -> 18580 | L7: =K7/J7 -> 0.39743316 | M7: =D7*0.8 -> 44000 | N7: =M7-C7 -> 15830 | O7: =N7/M7 -> 0.35977273 | P7: =D7*0.75 -> 41250 | Q7: =P7-C7 -> 13080 | R7: =Q7/P7 -> 0.31709091 | S7: =D7*0.7 -> 38500 | T7: =S7-C7 -> 10330 | U7: =T7/S7 -> 0.26831169 | V7: =1-C7/(0.85*D7) -> 0.39743316 | W7: =IF(V7>=0.3,"Resiste 30% OK",IF(V7>=0.25,"Resiste hasta 25%",IF(V7>=0.2,"Resiste hasta 20%",IF(V7>=0.15,"Resiste hasta 15%",IF(V7>=0.1,"Solo hasta 10%","No banca descuento"))))) -> Resiste 30% OK
A8: Buzo Cuello Redondo | B8: crewneck | C8: 26170 | D8: 43000
A9: Musculosa Bali | B9: tank | C9: 13096 | D9: 21800
A10: Remera Crop Mujer | B10: crop | C10: 15156 | D10: 23500
A11: Aura Oversize T-Shirt | B11: tee_oversize | C11: 20496 | D11: 31000
A12: Astra Oversize Hoodie | B12: hoodie_oversize | C12: 40000 | D12: 60000
A13: Aldea Classic Fit T-Shirt | B13: tee_classic | C13: 19696 | D13: 28600
A14: Remera Clásica Mujer | B14: tee_classic | C14: 19696 | D14: 28600
A17: 2) ESCENARIOS DE PACK — Facturación, utilidad bruta y margen% promedio por pack
A18: Supuesto: el pack se arma mezclando producto a precio actual y mismo %off para todas las prendas del pack. Se muestra por producto asumiendo pack homogéneo.
A20: Producto | B20: ESC A — 3u/10% 5u/20% 10u/30% | E20: ESC B — 3u/10% 5u/15% 10u/20% | H20: ESC C — 3u/10% 5u/20% 10u/25% | K20: ESC D — Propuesta: 3u/10% 5u/15% 10u/22%
B21: Util pack 3 | C21: Util pack 5 | D21: Util pack 10 | E21: Util pack 3 | F21: Util pack 5 | G21: Util pack 10 | H21: Util pack 3 | I21: Util pack 5 | J21: Util pack 10 | K21: Util pack 3 | L21: Util pack 5 | M21: Util pack 10
A22: =A7 -> Buzo Hoodie Unisex | B22: =3*(D7*0.9-C7) -> 63990 | C22: =5*(D7*0.8-C7) -> 79150 | D22: =10*(D7*0.7-C7) -> 103300 | E22: =3*(D7*0.9-C7) -> 63990 | F22: =5*(D7*0.85-C7) -> 92900 | G22: =10*(D7*0.8-C7) -> 158300 | H22: =3*(D7*0.9-C7) -> 63990 | I22: =5*(D7*0.8-C7) -> 79150 | J22: =10*(D7*0.75-C7) -> 130800 | K22: =3*(D7*0.9-C7) -> 63990 | L22: =5*(D7*0.85-C7) -> 92900 | M22: =10*(D7*0.78-C7) -> 147300
A23: =A8 -> Buzo Cuello Redondo | B23: =3*(D8*0.9-C8) -> 37590 | C23: =5*(D8*0.8-C8) -> 41150 | D23: =10*(D8*0.7-C8) -> 39300 | E23: =3*(D8*0.9-C8) -> 37590 | F23: =5*(D8*0.85-C8) -> 51900 | G23: =10*(D8*0.8-C8) -> 82300 | H23: =3*(D8*0.9-C8) -> 37590 | I23: =5*(D8*0.8-C8) -> 41150 | J23: =10*(D8*0.75-C8) -> 60800 | K23: =3*(D8*0.9-C8) -> 37590 | L23: =5*(D8*0.85-C8) -> 51900 | M23: =10*(D8*0.78-C8) -> 73700
A24: =A9 -> Musculosa Bali | B24: =3*(D9*0.9-C9) -> 19572 | C24: =5*(D9*0.8-C9) -> 21720 | D24: =10*(D9*0.7-C9) -> 21640 | E24: =3*(D9*0.9-C9) -> 19572 | F24: =5*(D9*0.85-C9) -> 27170 | G24: =10*(D9*0.8-C9) -> 43440 | H24: =3*(D9*0.9-C9) -> 19572 | I24: =5*(D9*0.8-C9) -> 21720 | J24: =10*(D9*0.75-C9) -> 32540 | K24: =3*(D9*0.9-C9) -> 19572 | L24: =5*(D9*0.85-C9) -> 27170 | M24: =10*(D9*0.78-C9) -> 39080
A25: =A10 -> Remera Crop Mujer | B25: =3*(D10*0.9-C10) -> 17982 | C25: =5*(D10*0.8-C10) -> 18220 | D25: =10*(D10*0.7-C10) -> 12940 | E25: =3*(D10*0.9-C10) -> 17982 | F25: =5*(D10*0.85-C10) -> 24095 | G25: =10*(D10*0.8-C10) -> 36440 | H25: =3*(D10*0.9-C10) -> 17982 | I25: =5*(D10*0.8-C10) -> 18220 | J25: =10*(D10*0.75-C10) -> 24690 | K25: =3*(D10*0.9-C10) -> 17982 | L25: =5*(D10*0.85-C10) -> 24095 | M25: =10*(D10*0.78-C10) -> 31740
A26: =A11 -> Aura Oversize T-Shirt | B26: =3*(D11*0.9-C11) -> 22212 | C26: =5*(D11*0.8-C11) -> 21520 | D26: =10*(D11*0.7-C11) -> 12040 | E26: =3*(D11*0.9-C11) -> 22212 | F26: =5*(D11*0.85-C11) -> 29270 | G26: =10*(D11*0.8-C11) -> 43040 | H26: =3*(D11*0.9-C11) -> 22212 | I26: =5*(D11*0.8-C11) -> 21520 | J26: =10*(D11*0.75-C11) -> 27540 | K26: =3*(D11*0.9-C11) -> 22212 | L26: =5*(D11*0.85-C11) -> 29270 | M26: =10*(D11*0.78-C11) -> 36840
A27: =A12 -> Astra Oversize Hoodie | B27: =3*(D12*0.9-C12) -> 42000 | C27: =5*(D12*0.8-C12) -> 40000 | D27: =10*(D12*0.7-C12) -> 20000 | E27: =3*(D12*0.9-C12) -> 42000 | F27: =5*(D12*0.85-C12) -> 55000 | G27: =10*(D12*0.8-C12) -> 80000 | H27: =3*(D12*0.9-C12) -> 42000 | I27: =5*(D12*0.8-C12) -> 40000 | J27: =10*(D12*0.75-C12) -> 50000 | K27: =3*(D12*0.9-C12) -> 42000 | L27: =5*(D12*0.85-C12) -> 55000 | M27: =10*(D12*0.78-C12) -> 68000
A28: =A13 -> Aldea Classic Fit T-Shirt | B28: =3*(D13*0.9-C13) -> 18132 | C28: =5*(D13*0.8-C13) -> 15920 | D28: =10*(D13*0.7-C13) -> 3240 | E28: =3*(D13*0.9-C13) -> 18132 | F28: =5*(D13*0.85-C13) -> 23070 | G28: =10*(D13*0.8-C13) -> 31840 | H28: =3*(D13*0.9-C13) -> 18132 | I28: =5*(D13*0.8-C13) -> 15920 | J28: =10*(D13*0.75-C13) -> 17540 | K28: =3*(D13*0.9-C13) -> 18132 | L28: =5*(D13*0.85-C13) -> 23070 | M28: =10*(D13*0.78-C13) -> 26120
A29: =A14 -> Remera Clásica Mujer | B29: =3*(D14*0.9-C14) -> 18132 | C29: =5*(D14*0.8-C14) -> 15920 | D29: =10*(D14*0.7-C14) -> 3240 | E29: =3*(D14*0.9-C14) -> 18132 | F29: =5*(D14*0.85-C14) -> 23070 | G29: =10*(D14*0.8-C14) -> 31840 | H29: =3*(D14*0.9-C14) -> 18132 | I29: =5*(D14*0.8-C14) -> 15920 | J29: =10*(D14*0.75-C14) -> 17540 | K29: =3*(D14*0.9-C14) -> 18132 | L29: =5*(D14*0.85-C14) -> 23070 | M29: =10*(D14*0.78-C14) -> 26120
A30: TOTAL | B30: =SUM(B22:B29) -> 239610 | C30: =SUM(C22:C29) -> 253600 | D30: =SUM(D22:D29) -> 215700 | E30: =SUM(E22:E29) -> 239610 | F30: =SUM(F22:F29) -> 326475 | G30: =SUM(G22:G29) -> 507200 | H30: =SUM(H22:H29) -> 239610 | I30: =SUM(I22:I29) -> 253600 | ... M30: =SUM(M22:M29) -> 448900
A33: 3) PROPUESTA FINAL — Escalera sugerida por familia de producto
A35: Familia / Producto | B35: Pack 3 | C35: Pack 5 | D35: Pack 10 | E35: Justificación
A36: POLÍTICA ESTÁNDAR (mayoría del catálogo) | B36: 0.1 | C36: 0.15 | D36: 0.22 | E36: Protege márgenes >15% en todas las prendas salvo las dos tees clásicas en negro
A37: Aldea Classic / Remera Clásica Mujer (color Negro) | B37: 0.1 | C37: 0.15 | D37: 0.15 | E37: Costo de estampa en negro sube margen base a 31%. Con 20% cae a 14%, con 30% queda en 1,6%. No entra al 22%.
A38: Astra Oversize Hoodie (premium $60k) | B38: 0.1 | C38: 0.15 | D38: 0.2 | E38: Costo al 66% del precio. Tolera hasta 21% con piso 15%. Además por posicionamiento premium no conviene 30% off.
A39: Buzo Hoodie Unisex (único que soporta 30%) | B39: 0.1 | C39: 0.15 | D39: 0.25 | E39: Margen base 49%. Si querés mostrar un 30% de gancho, este sí lo banca — pero subirlo a 25% ya es más que suficiente comercialmente.
A41: 4) RESPUESTAS DIRECTAS
A42: ¿Unificarías 100% el descuento para toda la línea? | B42: NO al 10/20/30. SÍ se puede unificar en 10/15/22 si acéptás sacar tees clásicas negras de la escalera.
A43: Escalera exacta que usaría | B43: 3 prendas: 10% off | 5 prendas: 15% off | 10 prendas: 22% off
A44: Qué prendas dejar afuera | B44: Aldea Classic T-Shirt NEGRO y Remera Clásica Mujer NEGRO: capar al 15% máximo (no entran al tier 10u/22%). Opcional: Astra premium a 20% en vez de 22% por imagen de marca.

Sheet Prompt_Bot
A1: # MENSAJE PARA EL DEV (contexto antes del prompt)
A3: Hola, te paso el system prompt actualizado para el bot de atención de Novamente. Algunas cosas importantes para que estés al tanto del contexto y el por qué del rediseño:
A5: ## Por qué cambió la tarifa
A6: Veníamos con una estructura de 3 tiers (Starter/Pro/Drop) y diferenciábamos costos internamente por color. Eso generaba dos problemas:
A7: 1. Inconsistencia comercial: el cliente recibía precios distintos según color, lo cual era confuso y nos obligaba a justificar diferencias internas que no queremos comunicar.
A8: 2. Falta de granularidad por volumen: con solo 3 escalones perdíamos a los clientes que pedían 1 sola unidad (B2C/on-demand) y a los que pedían 100+ (mayoristas).
A10: ## Qué cambió ahora
A11: - 5 tiers en lugar de 3: Modelo Partner (1u), Starter (5-9u), Pro (10-20u), Drop (30-99u), Bulk (100+u).
A12: - Precio único por producto, sin diferenciar por color.
A13: - Nombres comerciales: Berlin, Boston, Aura, Aldea Classic Fit, Buenos Aires, Bahamas, Bali.
A14: - Astra Oversize Hoodie discontinuado.
A15: - Boston (Hoodie Unisex) sumó 3 colores: Caramel, Crema, Gris Melange.
... A378: Te paso con un asesor que va a poder ayudarte mejor con eso. Me dejas tu nombre y un mail/WhatsApp?

Sheet Prompt_Dev_Costos
A1: PROMPT PARA EL DEV — Actualizacion de costos Dreamful + nuevo nivel Partners Growth Asunto: Actualizacion de costos de proveedor (Dreamful) y ajustes de precios — efectivo ya Hola, actualizamos los costos del proveedor Dreamful y necesito que los reflejes en la herramienta de costos. Cambian los costos de TODOS los SKU, los precios de venta de algunos tiers, y sumamos un nuevo nivel de cliente (Partners Growth). Te dejo TODO el detalle abajo, incluidos los tres niveles de costo segun cantidad de estampas. ================================================================ 1) NUEVOS COSTOS POR SKU — TRES NIVELES SEGUN ESTAMPA ================================================================ La herramienta maneja 3 costos por prenda segun el estampado: - Cost_1_Print : 1 estampa (1 ubicacion). - Chica : doble estampa, pero una de las dos estampas es chica (NO se refiere al talle de la prenda). - Cost_2_Print : 2 estampas (estampa completa). ESTE es el costo base que usa el modelo para margenes y para Growth. Formato: SKU - Producto - Color | Cost_1_Print / Chica / Cost_2_Print BB - Buzo Cuello Redondo - Blanco | 20.600 / 23.600 / 24.100 BN - Buzo Cuello Redondo - Negro | 23.170 / 26.170 / 28.170 BSW - Buzo Cuello Redondo - Stone Wash | 23.170 / 26.170 / 28.170 RCC - Remera Crop Mujer - Amarillo | 14.600 / 17.600 / 18.100 RCV - Remera Crop Mujer - Chocolate | 14.600 / 17.600 / 18.100 RCG - Remera Crop Mujer - Gris Melange | 14.600 / 17.600 / 18.100 RCN - Remera Crop Mujer - Negra | 14.600 / 17.600 / 18.100 HB - Buzo Hoodie Unisex - Blanco | 21.600 / 24.600 / 25.100 HN - Buzo Hoodie Unisex - Negro | 24.170 / 27.170 / 29.170 HSW - Buzo Hoodie Unisex - Stone Wash | 25.170 / 28.170 / 30.170 MMB - Musculosa Bali - Blanca | 14.600 / 17.600 / 18.100 MMG - Musculosa Bali - Gris | 14.600 / 17.600 / 18.100 RHB - Aldea Classic Fit - Blanco | 15.100 / 18.100 / 18.600 RHN - Aldea Classic Fit - Negro | 17.670 / 20.670 / 22.670 RMB - Remera Clasica Mujer - Blanca | 15.100 / 18.100 / 18.600 RMN - Remera Clasica Mujer - Negra | 17.670 / 20.670 / 22.670 ROB - Aura Oversize - Blanco | 15.500 / 18.500 / 19.000 RON - Aura Oversize - Negro | 18.070 / 21.070 / 23.070 ROSW - Aura Oversize - Stone Wash | 18.470 / 21.470 / 23.470 Referencia rapida del costo base (Cost_2_Print) anterior -> nuevo: Crewneck Blanco 22.100->24.100 | Crewneck Negro/SW 26.170->28.170 Crop (todos) 15.156->18.100 | Hoodie Blanco 23.100->25.100 Hoodie Negro 27.170->29.170 | Hoodie SW 28.170->30.170 Musculosa 13.096->18.100 | Classic/Mujer Blanco 15.656->18.600 Classic/Mujer Negro 19.696->22.670 | Oversize Blanco 16.500->19.000 Oversize Negro 20.096->23.070 | Oversize SW 20.496->23.470 Nota — colores extra sin costo propio en Dreamful (Hoodie Caramel/Crema/Gris y Oversize Caramel): se igualan al costo del color NEGRO de su categoria. Hoodie extras = 29.170 (Cost_2_Print), Oversize Caramel = 23.070. ================================================================ 2) PRECIOS DE VENTA QUE CAMBIAN (partners gratuitos / Starter) ================================================================ Regla aplicada: solo subimos el precio de los tiers cuyo margen quedaba NEGATIVO con el costo nuevo, llevandolos a ~4% sobre costo. El resto de los precios NO cambia. - Remera Crop Mujer (todos los colores): Drop 17.700 y Bulk 17.200 -> 18.800 ambos. - Aura Oversize Negro: Bulk 22.500 -> 24.000. - Aura Oversize Caramel: Bulk 22.500 -> 24.000. - Aura Oversize Stone Wash: Drop 23.200 -> 24.400, Bulk 22.500 -> 24.400. - Aldea Classic Negro: Bulk 21.700 -> 23.600. - Remera Clasica Mujer Negra: Bulk 21.700 -> 23.600. - Musculosa Bali (todos): quedo bajo costo en TODOS los tiers (costo +38%). Reprecificada completa, escalonada 8%->4% sobre costo: Partner 19.500 / Starter 19.400 / Pro 19.200 / Drop 19.000 / Bulk 18.800. Los precios B2C y los tiers no listados arriba se mantienen sin cambios. ================================================================ 3) NUEVO NIVEL DE CLIENTE: PARTNERS GROWTH (suscriptores pagos) ================================================================ Que es: nivel de precios para partners con suscripcion 'Growth'. Los precios actuales del modelo son para partners gratuitos/Starter; a los Growth se les ofrece precio CERCANO A NUESTRO COSTO como beneficio de la suscripcion. MECANISMO PARA IMPLEMENTAR/ACTUALIZAR EN LA PAGINA (deterministico, depende solo del costo base): Costo base = Cost_2_Print del SKU (mismo costo que usa el modelo). Partner (1u) = Costo base + 1.000 Starter (5-9u) = Costo base + 800 Pro (10-20u) = Costo base + 600 Drop (30-99u) = Costo base + 400 Bulk (100+u) = Costo base + 200 En palabras: el precio Growth arranca en +1.000 sobre el costo y baja 200 por cada escalon de volumen. El margen unitario en $ es FIJO por tier (1000/800/600/400/200) e independiente del producto. Implementacion sugerida: cuando el cliente es nivel Growth, calcular el precio on-the-fly como precio = costo_base + delta_tier, con delta_tier = { Partner:1000, Starter:800, Pro:600, Drop:400, Bulk:200 }. De esta forma los precios Growth se actualizan solos cada vez que cambian los costos, sin mantener una tabla aparte. Margen % resultante = delta_tier / (costo_base + delta_tier). Para SKU de costo alto, el Bulk queda en <1% de margen; es esperado (precio practicamente a costo). Descuento por cantidad: es leve a proposito (solo 200 por tier), porque el precio ya esta a costo y no hay margen para descontar mas en los niveles altos. ================================================================ 4) DONDE ENCONTRAR MAS INFO (pestanas de este Excel) ================================================================ - 'Precios Tab Dreamfull-sheets' : costos crudos del proveedor, los 3 niveles de estampa por SKU (Cost_1_Print / Chica / Cost_2_Print). - 'Detalle_SKU_Con_Margenes' : detalle por SKU y TALLE, con costo, precio por tier y margen $ y % de cada tier. El costo esta linkeado a la tab Dreamfull, recalcula solo. - 'Precios_Para_Comunicar' : resumen por SKU/color con precios de tier y margenes (partners gratuitos/Starter). - 'Resumen_por_Producto' : vista agregada por producto (costo min/max, precios tier, margenes min/max). - 'Precios_Partners_Growth' : tabla calculada del nuevo nivel Growth por SKU/color (precios y margenes). Avisame si queres el archivo Excel con el detalle por SKU/talle, o un export CSV de cualquiera de estas pestanas. | C1: PROMPT PARA EL DEV — ACTUALIZACION DE PRECIOS DE VENTA PARTNERS + GROWTH (ronda 2) Asunto: Nuevos precios de venta a partners y nuevo esquema Growth (precio unico por producto) Hola, actualizamos los precios de venta a partners. Dos cambios: (A) Subimos algunos precios de partner para que pasarse a Growth implique siempre un ahorro minimo del 8%. (B) El precio GROWTH pasa a ser UNICO por producto (ya no varia por color). ================================================================ 1) NUEVOS PRECIOS PARTNER (precio UNICO por producto, todos los tiers) ================================================================ Formato: Producto | Partner(1u) / Starter(5-9u) / Pro(10-20u) / Drop(30-99u) / Bulk(100+u) Buzo Cuello Redondo | 32.200 / 31.200 / 30.200 / 29.200 / 28.200 (SIN CAMBIO) Buzo Hoodie Unisex | 38.700 / 36.600 / 34.500 / 32.400 / 30.300 (SIN CAMBIO) Aura Oversize T-Shirt | 26.600 / 25.900 / 25.100 / 24.300 / 23.600 (subio) Aldea Classic Fit T-Shirt| 25.800 / 25.100 / 24.400 / 23.800 / 23.600 (subio) Remera Clasica Mujer | 25.800 / 25.100 / 24.400 / 23.800 / 23.600 (subio) Remera Crop Mujer | 20.800 / 20.300 / 19.800 / 19.300 / 18.900 (subio) Musculosa Bali | 20.800 / 20.700 / 20.500 / 20.300 / 20.100 (subio) Nota: estos precios son UNICOS por producto, aplican a todos los colores por igual. ================================================================ 2) NUEVO PRECIO GROWTH (suscriptores pagos) — UNICO POR PRODUCTO ================================================================ Cambio importante: el Growth deja de variar por color. Ahora es un precio unico por producto, calculado sobre el COSTO DEL COLOR MAS CARO + delta de tier. Regla de calculo: Costo base Growth = costo del color MAS CARO del producto (Cost_2_Print del color mas caro). Partner (1u) = Costo base + 1.000 Starter (5-9u) = Costo base + 800 Pro (10-20u) = Costo base + 600 Drop (30-99u) = Costo base + 400 Bulk (100+u) = Costo base + 200 Precios Growth resultantes por producto | Partner / Starter / Pro / Drop / Bulk: Buzo Cuello Redondo | 29.170 / 28.970 / 28.770 / 28.570 / 28.370 Buzo Hoodie Unisex | 31.170 / 30.970 / 30.770 / 30.570 / 30.370 Aura Oversize T-Shirt | 24.470 / 24.270 / 24.070 / 23.870 / 23.670 Aldea Classic Fit T-Shirt| 23.670 / 23.470 / 23.270 / 23.070 / 22.870 Remera Clasica Mujer | 23.670 / 23.470 / 23.270 / 23.070 / 22.870 Remera Crop Mujer | 19.100 / 18.900 / 18.700 / 18.500 / 18.300 Musculosa Bali | 19.100 / 18.900 / 18.700 / 18.500 / 18.300 ================================================================ 3) REGLA DEL 8% DE AHORRO (para mantener a futuro) ================================================================ El objetivo es que un partner que se suscribe a Growth ahorre como minimo 8% en el tier de entrada (Partner 1u) respecto del precio Partner normal. Regla: Precio Partner normal >= Precio Growth Partner / 0,92 (redondeado hacia arriba a la centena). Cuando cambien los costos, recalcular el Growth (costo color mas caro + delta) y verificar que el Partner normal siga cumpliendo esta condicion; si no, subir el Partner normal al minimo que la cumpla. ================================================================ 4) DONDE ENCONTRAR MAS INFO (pestanas del Excel) ================================================================ - 'Plan_Precios_Futuro' : tablas de comparacion antes/despues, regla del 8% y precios finales por tier (esta es la fuente de estos numeros). - 'Precios_Para_Comunicar' : precios partner actualizados por SKU/color con margenes. - 'Precios_Partners_Growth' : precios Growth unicos por producto con margenes. - 'Resumen_por_Producto' : vista agregada por producto. El detalle del cambio de COSTOS (Dreamful) esta en el prompt anterior, en la celda A1 de esta misma pestana.
